[
  {
    "date": "01-01-2025",
    "title": "Lịch công giáo ngày 01-01-2025",
    "desc": "Thánh Ma-ri-a, Ðức Mẹ Chúa Trời",
    "read": "Ds 6,22-27 ; GI 4,4-7 ; Lc 2,16-21",
    "paole": "Áo Lễ Linh Mục: Trắng"
  },
  {
    "date": "02-01-2025",
    "title": "Lịch công giáo ngày 02-01-2025",
    "desc": "Thánh Basiliô Cả và thánh Grêgôriô Nazianzênô, giám mục, tiến sĩ Hội Thánh",
    "read": "1 Ga 2,22-28 ; Ga 1,19-28",
    "paole": "Áo Lễ Linh Mục: Trắng"
  },
  {
    "date": "03-01-2025",
    "title": "Lịch công giáo ngày 03-01-2025",
    "desc": "Thứ Sáu trước Lễ Hiển Linh - Kính Danh rất thánh Chúa Giê-su",
    "read": "Pl 2,1-11 ; Lc 2,21-24",
    "paole": "Áo Lễ Linh Mục: Trắng"
  },
  {
    "date": "04-01-2025",
    "title": "Lịch công giáo ngày 04-01-2025",
    "desc": "Thứ Bảy trước Lễ Hiển Linh",
    "read": "s 60,1-6 ; Ep 3,2-3a.5-6 ; Mt 2,1-12",
    "paole": "Áo Lễ Linh Mục: Trắng"
  },
  {
    "date": "05-01-2025",
    "title": "Lịch công giáo ngày 05-01-2025",
    "desc": "Chúa Hiển Linh",
    "read": "s 60,1-6 ; Ep 3,2-3a.5-6 ; Mt 2,1-12 (Tr)",
    "paole": "Áo Lễ Linh Mục: Trắng"
  },
  {
    "date": "06-01-2025",
    "title": "Lịch công giáo ngày 06-01-2025",
    "desc": "Thứ Hai sau Lễ Hiển Linh",
    "read": "Ga 3,22–4,6 ; Mt 4,12-17.23-25 (Tr)",
    "paole": "Áo Lễ Linh Mục: Trắng"
  },
  {
    "date": "07-01-2025",
    "title": "Lịch công giáo ngày 07-01-2025",
    "desc": "Thứ Ba sau Lễ Hiển Linh - Thánh Rây-mun-đô Pê-nha-pho, linh mục",
    "read": "1 Ga 4, 7-10 ; Mc 6, 34-44 (Tr)",
    "paole": "Áo Lễ Linh Mục: Trắng"
  },
  {
    "date": "08-01-2025",
    "title": "Lịch công giáo ngày 08-01-2025",
    "desc": "Thứ Tư sau Lễ Hiển Linh",
    "read": "1 Ga 4,11-18 ; Mc 6,45-52 (Tr)",
    "paole": "Áo Lễ Linh Mục: Trắng"
  },
  {
    "date": "09-01-2025",
    "title": "Lịch công giáo ngày 09-01-2025",
    "desc": "Thứ Năm sau Lễ Hiển Linh",
    "read": "1 Ga 4,19–5,4 ; Lc 4,14-22a (Tr)",
    "paole": "Áo Lễ Linh Mục: Trắng"
  },
  {
    "date": "10-01-2025",
    "title": "Lịch công giáo ngày 10-01-2025",
    "desc": "Thứ Sáu sau Lễ Hiển Linh",
    "read": "1 Ga 5,5-13 ; Lc 5,12-16 (Tr)",
    "paole": "Áo Lễ Linh Mục: Trắng"
  },
  {
    "date": "11-01-2025",
    "title": "Lịch công giáo ngày 11-01-2025",
    "desc": "Thứ Bảy sau Lễ Hiển Linh",
    "read": "1 Ga 5,14-21 ; Ga 3,22-30 (Tr)",
    "paole": "Áo Lễ Linh Mục: Trắng"
  },
  {
    "date": "12-01-2025",
    "title": "Lịch công giáo ngày 12-01-2025",
    "desc": "Chúa Giê-su Chịu Phép Rửa",
    "read": "Is 42,1-4.6-7 (hay Is 40,1-5.9-11) ; Cv 10,34-38 (hay Tt 2,11-14 ; 3,4-7) ; Lc 3,15-16.21-22 (Tr)",
    "paole": "Áo Lễ Linh Mục: Trắng"
  },
  {
    "date": "13-01-2025",
    "title": "Lịch công giáo ngày 13-01-2025",
    "desc": "Thánh Hi-la-ri-ô, giám mục, tiến sĩ Hội Thánh",
    "read": "Dt 1,1-6 ; Mc 1,14-20 (X)",
    "paole": "Áo Lễ Linh Mục: Xanh"
  },
  {
    "date": "14-01-2025",
    "title": "Lịch công giáo ngày 14-01-2025",
    "desc": "Thứ Ba trong tuần thứ Nhất Mùa Quanh Năm",
    "read": "Dt 2,5-12 ; Mc 1,21-28 (X)",
    "paole": "Áo Lễ Linh Mục: Xanh"
  },
  {
    "date": "15-01-2025",
    "title": "Lịch công giáo ngày 15-01-2025",
    "desc": "Thứ Tư trong tuần thứ Nhất Mùa Quanh Năm",
    "read": "Dt 2,14-18 ; Mc 1,29-39 (X)",
    "paole": "Áo Lễ Linh Mục: Xanh"
  },
  {
    "date": "16-01-2025",
    "title": "Lịch công giáo ngày 16-01-2025",
    "desc": "Thứ Năm trong tuần thứ Nhất Mùa Quanh Năm",
    "read": "Dt 3,7-14 ; Mc 1,40-45 (X)",
    "paole": "Áo Lễ Linh Mục: Xanh"
  },
  {
    "date": "17-01-2025",
    "title": "Lịch công giáo ngày 17-01-2025",
    "desc": "Thánh An-tôn, viện phụ",
    "read": "Dt 4,1-5,11 ; Mc 2,1-12 (Tr)",
    "paole": "Áo Lễ Linh Mục: Trắng"
  },
  {
    "date": "18-01-2025",
    "title": "Lịch công giáo ngày 18-01-2025",
    "desc": "Lễ Đức Mẹ ngày thứ bảy",
    "read": "Dt 4,12-16 ; Mc 2,13-17 (X)",
    "paole": "Áo Lễ Linh Mục: Xanh"
  },
  {
    "date": "19-01-2025",
    "title": "Lịch công giáo ngày 19-01-2025",
    "desc": "Chúa Nhật thứ Hai Mùa Quanh Năm",
    "read": "Is 62,1-5 ; 1 Cr 12,4-11 ; Ga 2,1-11 (X)",
    "paole": "Áo Lễ Linh Mục: Xanh"
  },
  {
    "date": "20-01-2025",
    "title": "Lịch công giáo ngày 20-01-2025",
    "desc": "Thứ Hai trong tuần thứ Hai Mùa Quanh Năm",
    "read": "Dt 5,1-10 ; Mc 2,18-22 (X)",
    "paole": "Áo Lễ Linh Mục: Xanh"
  },
  {
    "date": "21-01-2025",
    "title": "Lịch công giáo ngày 21-01-2025",
    "desc": "Thánh A-nê, trinh nữ, tử đạo",
    "read": "Dt 6,10-20 ; Mc 2,23-28 (Đ)",
    "paole": "Áo Lễ Linh Mục: Đỏ"
  },
  {
    "date": "22-01-2025",
    "title": "Lịch công giáo ngày 22-01-2025",
    "desc": "Thánh Vinh-sơn, phó tế, tử đạo",
    "read": "Dt 7,1-3.15-17 ; Mc 3,1-6 (X)",
    "paole": "Áo Lễ Linh Mục: Xanh"
  },
  {
    "date": "23-01-2025",
    "title": "Lịch công giáo ngày 23-01-2025",
    "desc": "Thứ Năm trong tuần thứ Hai Mùa Quanh Năm",
    "read": "Dt 7,25–8,6 ; Mc 3,7-12 (X)",
    "paole": "Áo Lễ Linh Mục: Xanh"
  },
  {
    "date": "24-01-2025",
    "title": "Lịch công giáo ngày 24-01-2025",
    "desc": "Thánh Phan-xi-cô đơ Xan, giám mục, tiến sĩ Hội Thánh",
    "read": "Dt 8,6-13 ; Mc 3,13-19 (Tr)",
    "paole": "Áo Lễ Linh Mục: Trắng"
  },
  {
    "date": "25-01-2025",
    "title": "Lịch công giáo ngày 25-01-2025",
    "desc": "Thánh Phao-lô, tông đồ trở lại",
    "read": "Cv 22,3-16 (hay Cv 9,1-22) ; Mc 16,15-18 (Tr)",
    "paole": "Áo Lễ Linh Mục: Trắng"
  },
  {
    "date": "26-01-2025",
    "title": "Lịch công giáo ngày 26-01-2025",
    "desc": "Chúa Nhật thứ Ba Mùa Quanh Năm",
    "read": "Nkm 8,2-4a.5-6.8-10 ; 1 Cr 12,12-30 (hay 1 Cr 12,12-14.27) ; Lc 1,1-4 ; 4,14-21 (X)",
    "paole": "Áo Lễ Linh Mục: Xanh"
  },
  {
    "date": "27-01-2025",
    "title": "Lịch công giáo ngày 27-01-2025",
    "desc": "Thánh An-giê-la Mê-ri-si, trinh nữ",
    "read": "Dt 9,15.24-28 ; Mc 3,22-30 (X)",
    "paole": "Áo Lễ Linh Mục: Xanh"
  },
  {
    "date": "28-01-2025",
    "title": "Lịch công giáo ngày 28-01-2025",
    "desc": "Thánh Tô-ma A-qui-nô, linh mục, tiến sĩ Hội Thánh",
    "read": "Dt 10,1-10 ; Mc 3,31-35 (Tr)",
    "paole": "Áo Lễ Linh Mục: Trắng"
  },
  {
    "date": "29-01-2025",
    "title": "Lịch công giáo ngày 29-01-2025",
    "desc": "MỒNG MỘT TẾT ẤT TỴ. CẦU BÌNH AN CHO NĂM MỚI",
    "read": "Dt 10,11-18 ; Mc 4,1-20 (X) , Được cử hành lễ ngoại lịch (IM 376) (Tr). Lễ Giao Thừa: Ds 6,22-27 ; 1 Tx 5,16-26.28 ; Mt 5,1-10. Lễ Tân Niên: St 1,14-18 (hay Is 65,17-21 hay Is 11,1-9) ; Pl 4,4-8 (hay Kh 21,1-6 hay Cl 3,12-17) ; Mt 6,25-34 (hay Mt 5,43-48 hay Ga 14,23-27)",
    "paole": "Áo Lễ Linh Mục: Xanh"
  },
  {
    "date": "30-01-2025",
    "title": "Lịch công giáo ngày 30-01-2025",
    "desc": "MỒNG HAI TẾT. KÍNH NHỚ TỔ TIÊN VÀ ÔNG BÀ CHA MẸ. Thánh Tôma Ngô Túc Khuông, linh mục, tử đạo",
    "read": "Dt 10,19-25 ; Mc 4,21-25 (X)",
    "paole": "Áo Lễ Linh Mục: Xanh"
  },
  {
    "date": "31-01-2025",
    "title": "Lịch công giáo ngày 31-01-2025",
    "desc": "MỒNG BA TẾT. THÁNH HOÁ CÔNG ĂN VIỆC LÀM. Thánh Gioan Bosco, linh mục",
    "read": "Dt 10,32-39 ; Mc 4,26-34 (Tr)",
    "paole": "Áo Lễ Linh Mục: Trắng"
  },
  {
    "date": "01-02-2025",
    "title": "Lịch công giáo ngày 01-02-2025",
    "desc": "Thứ Bảy trong tuần thứ Ba Mùa Quanh Năm",
    "read": "Dt 11,1-2.8-19 ; Mc 4,35-41 (X)",
    "paole": "Áo Lễ Linh Mục: Xanh"
  },
  {
    "date": "02-02-2025",
    "title": "Lịch công giáo ngày 02-02-2025",
    "desc": "CHÚA NHẬT IV THƯỜNG NIÊN. DÂNG CHÚA GIÊSU TRONG ĐỀN THÁNH (LỄ NẾN)",
    "read": "Ml 3,1-4 ; Dt 2,14-18 ; Lc 2,22-40 (hay Lc 2,22-32) (Tr)",
    "paole": "Áo Lễ Linh Mục: Trắng"
  },
  {
    "date": "03-02-2025",
    "title": "Lịch công giáo ngày 03-02-2025",
    "desc": "Thánh vịnh tuần IV. Thánh Blasiô, giám mục, tử đạo. Thánh Ansgariô, giám mục",
    "read": "Dt 11,32-40 ; Mc 5,1-20 (X)",
    "paole": "Áo Lễ Linh Mục: Xanh"
  },
  {
    "date": "04-02-2025",
    "title": "Lịch công giáo ngày 04-02-2025",
    "desc": "Thứ Ba trong tuần thứ Tư Mùa Quanh Năm",
    "read": "Dt 12,1-4 ; Mc 5,21-43 (X)",
    "paole": "Áo Lễ Linh Mục: Xanh"
  },
  {
    "date": "05-02-2025",
    "title": "Lịch công giáo ngày 05-02-2025",
    "desc": "Thánh Agatha, trinh nữ, tử đạo",
    "read": "Dt 12,4-7.11-15 ; Mc 6,1-6 (Đ)",
    "paole": "Áo Lễ Linh Mục: Đỏ"
  },
  {
    "date": "06-02-2025",
    "title": "Lịch công giáo ngày 06-02-2025",
    "desc": "Thánh Phaolô Miki và các bạn, tử đạo",
    "read": "Dt 12,18-19.21-24 ; Mc 6,7-13 (Đ)",
    "paole": "Áo Lễ Linh Mục: Đỏ"
  },
  {
    "date": "07-02-2025",
    "title": "Lịch công giáo ngày 07-02-2025",
    "desc": "Thứ Sáu trong tuần thứ Tư Mùa Quanh Năm",
    "read": "Dt 13,1-8 ; Mc 6,14-29 (X)",
    "paole": "Áo Lễ Linh Mục: Xanh"
  },
  {
    "date": "08-02-2025",
    "title": "Lịch công giáo ngày 08-02-2025",
    "desc": "Thánh Giêrônimô Êmilianô; Thánh Jôsêphina Bakhita, trinh nữ",
    "read": "Dt 13,15-17.20-21 ; Mc 6,30-34 (X)",
    "paole": "Áo Lễ Linh Mục: Xanh"
  },
  {
    "date": "09-02-2025",
    "title": "Lịch công giáo ngày 09-02-2025",
    "desc": "CHÚA NHẬT V THƯỜNG NIÊN. Thánh Vịnh Tuần I",
    "read": "Is 6,1-2a.3-8 ; 1 Cr 15,1-11 (hay 1 Cr 15,3-8.11) ; Lc 5,1-11 (X)",
    "paole": "Áo Lễ Linh Mục: Xanh"
  },
  {
    "date": "10-02-2025",
    "title": "Lịch công giáo ngày 10-02-2025",
    "desc": "Thánh Scholastica, trinh nữ. Lễ nhớ",
    "read": "St 1,1-19 ; Mc 6,53-56 (Tr)",
    "paole": "Áo Lễ Linh Mục: Trắng"
  },
  {
    "date": "11-02-2025",
    "title": "Lịch công giáo ngày 11-02-2025",
    "desc": "Đức Mẹ Lộ Đức (Tr). Ngày Quốc Tế Bệnh Nhân. Thánh Tôma Ngô Túc Khuông, linh mục, tử đạo",
    "read": "St 1,20–2,4a ; Mc 7,1-13. Lễ Đức Mẹ: Is 66,10-14c ; Ga 2,1-11 (X)",
    "paole": "Áo Lễ Linh Mục: Xanh"
  },
  {
    "date": "12-02-2025",
    "title": "Lịch công giáo ngày 12-02-2025",
    "desc": "Thứ Tư trong tuần thứ Năm Mùa Quanh Năm",
    "read": "St 2,4b-9.15-17 ; Mc 7,14-23 (X)",
    "paole": "Áo Lễ Linh Mục: Xanh"
  },
  {
    "date": "13-02-2025",
    "title": "Lịch công giáo ngày 13-02-2025",
    "desc": "Thánh Phaolô Lê Văn Lộc, linh mục, tử đạo",
    "read": "Thánh Phaolô Lê Văn Lộc, linh mục, tử đạo",
    "paole": "Áo Lễ Linh Mục: Xanh"
  },
  {
    "date": "14-02-2025",
    "title": "Lịch công giáo ngày 14-02-2025",
    "desc": "Thánh Cyrillô, đan sĩ và thánh Mêthôđiô, giám mục",
    "read": "St 3,1-8 ; Mc 7,31-37 (Tr)",
    "paole": "Áo Lễ Linh Mục: Trắng"
  },
  {
    "date": "15-02-2025",
    "title": "Lịch công giáo ngày 15-02-2025",
    "desc": "Thứ Bảy trong tuần thứ Năm Mùa Quanh Năm",
    "read": "St 3,9-24 ; Mc 8,1-10 (X)",
    "paole": "Áo Lễ Linh Mục: Xanh"
  },
  {
    "date": "16-02-2025",
    "title": "Lịch công giáo ngày 16-02-2025",
    "desc": "CHÚA NHẬT VI THƯỜNG NIÊN. Thánh Vịnh Tuần II",
    "read": "Gr 17,5-8 ; 1 Cr 15,12.16-20 ; Lc 6,17.20-26 (X)",
    "paole": "Áo Lễ Linh Mục: Xanh"
  },
  {
    "date": "17-02-2025",
    "title": "Lịch công giáo ngày 17-02-2025",
    "desc": "Bảy thánh lập dòng Tôi Tớ Đức Trinh Nữ Maria",
    "read": "St 4,1-15.25 ; Mc 8,11-13 (X)",
    "paole": "Áo Lễ Linh Mục: Xanh"
  },
  {
    "date": "18-02-2025",
    "title": "Lịch công giáo ngày 18-02-2025",
    "desc": "Thứ Ba trong tuần thứ Sáu Mùa Quanh Năm",
    "read": "St 6,5-8 ; 7,1-5.10 ; Mc 8,14-21 (X)",
    "paole": "Áo Lễ Linh Mục: Xanh"
  },
  {
    "date": "19-02-2025",
    "title": "Lịch công giáo ngày 19-02-2025",
    "desc": "Thứ Tư trong tuần thứ Sáu Mùa Quanh Năm",
    "read": "St 8,6-13.20-22 ; Mc 8,22-26 (X)",
    "paole": "Áo Lễ Linh Mục: Xanh"
  },
  {
    "date": "20-02-2025",
    "title": "Lịch công giáo ngày 20-02-2025",
    "desc": "Thứ Năm trong tuần thứ Sáu Mùa Quanh Năm",
    "read": "St 9,1-13 ; Mc 8,27-33 (X)",
    "paole": "Áo Lễ Linh Mục: Xanh"
  },
  {
    "date": "21-02-2025",
    "title": "Lịch công giáo ngày 21-02-2025",
    "desc": "Thánh Phêrô Đamianô, giám mục, tiến sĩ Hội Thánh",
    "read": "St 11,1-9 ; Mc 8,34–9,1 (X)",
    "paole": "Áo Lễ Linh Mục: Xanh"
  },
  {
    "date": "22-02-2025",
    "title": "Lịch công giáo ngày 22-02-2025",
    "desc": "LẬP TÔNG TOÀ THÁNH PHÊRÔ",
    "read": "1 Pr 5,1-4 ; Mt 16,13-19 (Tr)",
    "paole": "Áo Lễ Linh Mục: Trắng"
  },
  {
    "date": "23-02-2025",
    "title": "Lịch công giáo ngày 23-02-2025",
    "desc": "CHÚA NHẬT VII THƯỜNG NIÊN. Thánh Vịnh Tuần III",
    "read": "Sm 26,2.7-9.12-13.22-23 ; 1 Cr 15,45-49 ; Lc 6,27-38 (X)",
    "paole": "Áo Lễ Linh Mục: Trắng"
  },
  {
    "date": "24-02-2025",
    "title": "Lịch công giáo ngày 24-02-2025",
    "desc": "Thứ Hai trong tuần thứ Bảy Mùa Quanh Năm",
    "read": "Hc 1,1-10 ; Mc 9,14-29 (X)",
    "paole": "Áo Lễ Linh Mục: Xanh"
  },
  {
    "date": "25-02-2025",
    "title": "Lịch công giáo ngày 25-02-2025",
    "desc": "Thứ Ba trong tuần thứ Bảy Mùa Quanh Năm",
    "read": "Hc 2,1-11 ; Mc 9,30-37 (X)",
    "paole": "Áo Lễ Linh Mục: Xanh"
  },
  {
    "date": "26-02-2025",
    "title": "Lịch công giáo ngày 26-02-2025",
    "desc": "Thứ Tư trong tuần thứ Bảy Mùa Quanh Năm",
    "read": "Hc 4,11-19 ; Mc 9,38-40 (X)",
    "paole": "Áo Lễ Linh Mục: Xanh"
  },
  {
    "date": "27-02-2025",
    "title": "Lịch công giáo ngày 27-02-2025",
    "desc": "Thánh Grêgôriô Naracensiô, viện phụ, tiến sĩ Hội Thánh",
    "read": "Hc 5,1-8 ; Mc 9,41-50 (X)",
    "paole": "Áo Lễ Linh Mục: Xanh"
  },
  {
    "date": "28-02-2025",
    "title": "Lịch công giáo ngày 28-02-2025",
    "desc": "Thứ Sáu trong tuần thứ Bảy Mùa Quanh Năm",
    "read": "Hc 6,5-17 ; Mc 10,1-12 (X)",
    "paole": "Áo Lễ Linh Mục: Xanh"
  },
  {
    "date": "01-03-2025",
    "title": "Lịch công giáo ngày 01-03-2025",
    "desc": "Thứ Bảy trong tuần thứ Bảy Mùa Quanh Năm",
    "read": "Hc 17,1-15 ; Mc 10,13-16 (X)",
    "paole": "Áo Lễ Linh Mục: Xanh"
  },
  {
    "date": "02-03-2025",
    "title": "Lịch công giáo ngày 02-03-2025",
    "desc": "CHÚA NHẬT VIII THƯỜNG NIÊN. Thánh vịnh tuần IV",
    "read": "Hc 27,4-7 ; 1 Cr 15,54-58 ; Lc 6,39-45 (X)",
    "paole": "Áo Lễ Linh Mục: Xanh"
  },
  {
    "date": "03-03-2025",
    "title": "Lịch công giáo ngày 03-03-2025",
    "desc": "Thứ Hai trong tuần thứ Tám Mùa Quanh Năm",
    "read": "Hc 17,20-28 ; Mc 10,17-27 (X)",
    "paole": "Áo Lễ Linh Mục: Xanh"
  },
  {
    "date": "04-03-2025",
    "title": "Lịch công giáo ngày 04-03-2025",
    "desc": "Thánh Casimirô",
    "read": "Hc 35,1-12 ; Mc 10,28-31 (X)",
    "paole": "Áo Lễ Linh Mục: Xanh"
  },
  {
    "date": "05-03-2025",
    "title": "Lịch công giáo ngày 05-03-2025",
    "desc": "LỄ TRO. Thánh vịnh tuần IV. Giữ chay và kiêng thịt",
    "read": "Ge 2,12-18 ; 2 Cr 5,20–6,2 ; Mt 6,1-6.16-18 (Tm)",
    "paole": "Áo Lễ Linh Mục: Tím"
  },
  {
    "date": "06-03-2025",
    "title": "Lịch công giáo ngày 06-03-2025",
    "desc": "Thứ Năm sau Thứ Tư Lễ Tro",
    "read": "Đnl 30,15-20 ; Lc 9,22-25 (Tm)",
    "paole": "Áo Lễ Linh Mục: Tím"
  },
  {
    "date": "07-03-2025",
    "title": "Lịch công giáo ngày 07-03-2025",
    "desc": "Thánh nữ Perpêtua và thánh nữ Fêlicita, tử đạo",
    "read": "Is 58,1-9a ; Mt 9,14-15 (Tm)",
    "paole": "Áo Lễ Linh Mục: Tím"
  },
  {
    "date": "08-03-2025",
    "title": "Lịch công giáo ngày 08-03-2025",
    "desc": "Thánh Gioan Thiên Chúa, tu sĩ",
    "read": "Is 58,9b-14 ; Lc 5,27-32 (Tm)",
    "paole": "Áo Lễ Linh Mục: Tím"
  },
  {
    "date": "09-03-2025",
    "title": "Lịch công giáo ngày 09-03-2025",
    "desc": "CHÚA NHẬT I MÙA CHAY. Thánh vịnh tuần I",
    "read": "Đnl 26,4-10 ; Rm 10,8-13 ; Lc 4,1-13 (Tm)",
    "paole": "Áo Lễ Linh Mục: Tím"
  },
  {
    "date": "10-03-2025",
    "title": "Lịch công giáo ngày 10-03-2025",
    "desc": "Thứ Hai trong tuần thứ Nhất Mùa Chay",
    "read": "Lv 19,1-2.11-18 ; Mt 25,31-46 (Tm)",
    "paole": "Áo Lễ Linh Mục: Tím"
  },
  {
    "date": "11-03-2025",
    "title": "Lịch công giáo ngày 11-03-2025",
    "desc": "Thánh Đaminh Nguyễn Văn Cẩm, linh mục, tử đạo",
    "read": "Is 55,10-11 ; Mt 6:7-15 (Tm)",
    "paole": "Áo Lễ Linh Mục: Tím"
  },
  {
    "date": "12-03-2025",
    "title": "Lịch công giáo ngày 12-03-2025",
    "desc": "Thứ Tư trong tuần thứ Nhất Mùa Chay",
    "read": "Gn 3,1-10 ; Lc 11,29-32 (Tm)",
    "paole": "Áo Lễ Linh Mục: Tím"
  },
  {
    "date": "13-03-2025",
    "title": "Lịch công giáo ngày 13-03-2025",
    "desc": "Kỷ niệm 12 năm ngày Đức Phanxicô được bầu làm Giáo Hoàng (2013)",
    "read": "Et 4,17k-17m.17r-17t ; Mt 7,7-12 (Tm)",
    "paole": "Áo Lễ Linh Mục: Tím"
  },
  {
    "date": "14-03-2025",
    "title": "Lịch công giáo ngày 14-03-2025",
    "desc": "Thứ Sáu trong tuần thứ Nhất Mùa Chay",
    "read": "Ed 18,21-28 ; Mt 5,20-26 (Tm)",
    "paole": "Áo Lễ Linh Mục: Tím"
  },
  {
    "date": "15-03-2025",
    "title": "Lịch công giáo ngày 15-03-2025",
    "desc": "Thứ Bảy trong tuần thứ Nhất Mùa Chay",
    "read": "Đnl 26,16-19 ; Mt 5,43-48 (Tm)",
    "paole": "Áo Lễ Linh Mục: Tím"
  },
  {
    "date": "16-03-2025",
    "title": "Lịch công giáo ngày 16-03-2025",
    "desc": "CHÚA NHẬT II MÙA CHAY. Thánh vịnh tuần II",
    "read": "St 15,5-12.17-18 ; Pl 3,17–4,1 (hay Pl 3,20–4,1) ; Lc 9,28b-36 (Tm)",
    "paole": "Áo Lễ Linh Mục: Tím"
  },
  {
    "date": "17-03-2025",
    "title": "Lịch công giáo ngày 17-03-2025",
    "desc": "Thánh Patriciô, giám mục",
    "read": "Đn 9,4b-10 ; Lc 6,36-38 (Tm)",
    "paole": "Áo Lễ Linh Mục: Tím"
  },
  {
    "date": "18-03-2025",
    "title": "Lịch công giáo ngày 18-03-2025",
    "desc": "Thánh Cyrillô Giêrusalem, giám mục, tiến sĩ Hội Thánh",
    "read": "Is 1,10.16-20 ; Mt 23,1-12 (Tm)",
    "paole": "Áo Lễ Linh Mục: Tím"
  },
  {
    "date": "19-03-2025",
    "title": "Lịch công giáo ngày 19-03-2025",
    "desc": "THÁNH GIUSE, BẠN TRĂM NĂM ĐỨC MARIA. Bổn mạng Hội Thánh hoàn vũ, Hội Thánh Việt Nam",
    "read": "2 Sm 7,4-5a.12-14a.16 ; Rm 4,13.16-18.22 ; Mt 1,16.18-21.24a (hay Lc 2,41-51a) (Tr)",
    "paole": "Áo Lễ Linh Mục: Trắng"
  },
  {
    "date": "20-03-2025",
    "title": "Lịch công giáo ngày 20-03-2025",
    "desc": "Thứ Năm trong tuần thứ Hai Mùa Chay",
    "read": "Gr 17,5-10 ; Lc 16,19-31 (Tm)",
    "paole": "Áo Lễ Linh Mục: Tím"
  },
  {
    "date": "21-03-2025",
    "title": "Lịch công giáo ngày 21-03-2025",
    "desc": "Thứ Sáu trong tuần thứ Hai Mùa Chay",
    "read": "St 37,3-4.12-13a.17b-28 ; Mt 21,33-43.45-46 (Tm)",
    "paole": "Áo Lễ Linh Mục: Tím"
  },
  {
    "date": "22-03-2025",
    "title": "Lịch công giáo ngày 22-03-2025",
    "desc": "Thứ Bảy trong tuần thứ Hai Mùa Chay",
    "read": "Mk 7,14-15.18-20 ; Lc 15,1-3.11-32 (Tm)",
    "paole": "Áo Lễ Linh Mục: Tím"
  },
  {
    "date": "23-03-2025",
    "title": "Lịch công giáo ngày 23-03-2025",
    "desc": "CHÚA NHẬT III MÙA CHAY. Thánh vịnh tuần III",
    "read": "Xh 3,1-8a.13-15 ; 1 Cr 10,1-6.10-12 ; Lc 13,1-9 (Tm)",
    "paole": "Áo Lễ Linh Mục: Tím"
  },
  {
    "date": "24-03-2025",
    "title": "Lịch công giáo ngày 24-03-2025",
    "desc": "Thứ Hai trong tuần thứ Ba Mùa Chay",
    "read": "2 V 5,1-15a ; Lc 4,24-30 (Tm)",
    "paole": "Áo Lễ Linh Mục: Tím"
  },
  {
    "date": "25-03-2025",
    "title": "Lịch công giáo ngày 25-03-2025",
    "desc": "LỄ TRUYỀN TIN",
    "read": "Is 7,10-14 ; 8,10 ; Đt 10,4-10 ; Lc 1,26-38 (Tr)",
    "paole": "Áo Lễ Linh Mục: Trắng"
  },
  {
    "date": "26-03-2025",
    "title": "Lịch công giáo ngày 26-03-2025",
    "desc": "Thứ Tư trong tuần thứ Ba Mùa Chay",
    "read": "Đnl 4,1.5-9 ; Mt 5,17-19 (Tm)",
    "paole": "Áo Lễ Linh Mục: Tím"
  },
  {
    "date": "27-03-2025",
    "title": "Lịch công giáo ngày 27-03-2025",
    "desc": "Thứ Năm trong tuần thứ Ba Mùa Chay",
    "read": "Gr 7,23-28 ; Lc 11,14-23 (Tm)",
    "paole": "Áo Lễ Linh Mục: Tím"
  },
  {
    "date": "28-03-2025",
    "title": "Lịch công giáo ngày 28-03-2025",
    "desc": "Thứ Sáu trong tuần thứ Ba Mùa Chay",
    "read": "Hs 14,2-10 ; Mc 12,28b-34 (Tm)",
    "paole": "Áo Lễ Linh Mục: Tím"
  },
  {
    "date": "29-03-2025",
    "title": "Lịch công giáo ngày 29-03-2025",
    "desc": "Thứ Bảy trong tuần thứ Ba Mùa Chay",
    "read": "Hs 6,1-6 ; Lc 18,9-14 (Tm)",
    "paole": "Áo Lễ Linh Mục: Tím"
  },
  {
    "date": "30-03-2025",
    "title": "Lịch công giáo ngày 30-03-2025",
    "desc": "CHÚA NHẬT IV MÙA CHAY. Thánh vịnh tuần IV",
    "read": "Gs 5,9a.10-12 ; 2 Cr 5,17-21 ; Lc 15,1-3.11-32 (Tm)",
    "paole": "Áo Lễ Linh Mục: Tím"
  },
  {
    "date": "31-03-2025",
    "title": "Lịch công giáo ngày 31-03-2025",
    "desc": "Thứ Hai trong tuần thứ Tư Mùa Chay",
    "read": "Is 65,17-21 ; Ga 4,43-54 (Tm)",
    "paole": "Áo Lễ Linh Mục: Tím"
  },
  {
    "date": "01-04-2025",
    "title": "Lịch công giáo ngày 01-04-2025",
    "desc": "Thứ Ba trong tuần thứ Tư Mùa Chay",
    "read": "Ed 47,1-9.12 ; Ga 5,1-3a.5-16 (Tm)",
    "paole": "Áo Lễ Linh Mục: Tím"
  },
  {
    "date": "02-04-2025",
    "title": "Lịch công giáo ngày 02-04-2025",
    "desc": "Thánh Phanxicô Paola, ẩn tu. Thánh Đaminh Vũ Đình Tước, linh mục, tử đạo (1839)",
    "read": "Is 49,8-15 ; Ga 5,17-30 (Tm)",
    "paole": "Áo Lễ Linh Mục: Tím"
  },
  {
    "date": "03-04-2025",
    "title": "Lịch công giáo ngày 03-04-2025",
    "desc": "Thứ Năm trong tuần thứ Tư Mùa Chay",
    "read": "Xh 32,7-14 ; Ga 5,31-47 (Tm)",
    "paole": "Áo Lễ Linh Mục: Tím"
  },
  {
    "date": "04-04-2025",
    "title": "Lịch công giáo ngày 04-04-2025",
    "desc": "Thánh Isiđôrô, giám mục, tiến sĩ Hội Thánh",
    "read": "Kn 2,1a.12-22 ; Ga 7,1-2.10.25-30 (Tm)",
    "paole": "Áo Lễ Linh Mục: Tím"
  },
  {
    "date": "05-04-2025",
    "title": "Lịch công giáo ngày 05-04-2025",
    "desc": "Thánh Vinh Sơn Ferrer, linh mục",
    "read": "Gr 11,18-20 ; Ga 7,40-53 (Tm)",
    "paole": "Áo Lễ Linh Mục: Tím"
  },
  {
    "date": "06-04-2025",
    "title": "Lịch công giáo ngày 06-04-2025",
    "desc": "CHÚA NHẬT V MÙA CHAY. Thánh Vịnh Tuần I",
    "read": "s 43,16-21 ; Pl 3,8-14 ; Ga 8,1-11 (Tm)",
    "paole": "Áo Lễ Linh Mục: Tím"
  },
  {
    "date": "07-04-2025",
    "title": "Lịch công giáo ngày 07-04-2025",
    "desc": "Thánh Gioan Baoti xita Lasan, linh mục.",
    "read": "Đn 13,1-9.15-17.19-30.33-62 (hay Đn 13,41c-62) ; Ga 8,12-20 (Tm)",
    "paole": "Áo Lễ Linh Mục: Tím"
  },
  {
    "date": "08-04-2025",
    "title": "Lịch công giáo ngày 08-04-2025",
    "desc": "Thứ Ba trong tuần thứ Năm Mùa Chay",
    "read": "Ds 21,4-9 ; Ga 8,21-30 (Tm)",
    "paole": "Áo Lễ Linh Mục: Tím"
  },
  {
    "date": "09-04-2025",
    "title": "Lịch công giáo ngày 09-04-2025",
    "desc": "Thứ Tư trong tuần thứ Năm Mùa Chay",
    "read": "Đn 3,14-20.91-92.95 (hay Đn 3,14-20.24-25.28) ; Ga 8,31-42 (Tm)",
    "paole": "Áo Lễ Linh Mục: Tím"
  },
  {
    "date": "10-04-2025",
    "title": "Lịch công giáo ngày 10-04-2025",
    "desc": "Thứ Năm trong tuần thứ Năm Mùa Chay",
    "read": "St 17,3-9 ; Ga 8,51-59 (Tm)",
    "paole": "Áo Lễ Linh Mục: Tím"
  },
  {
    "date": "11-04-2025",
    "title": "Lịch công giáo ngày 11-04-2025",
    "desc": "Thánh Stanislaô, giám mục, tử đạo",
    "read": "Gr 20,10-13 ; Ga 10,31-42 (Tm)",
    "paole": "Áo Lễ Linh Mục: Tím"
  },
  {
    "date": "12-04-2025",
    "title": "Lịch công giáo ngày 12-04-2025",
    "desc": "Thứ Bảy trong tuần thứ Năm Mùa Chay",
    "read": "Ed 37,21-28 ; Ga 11,45-56 (Tm)",
    "paole": "Áo Lễ Linh Mục: Tím"
  },
  {
    "date": "13-04-2025",
    "title": "Lịch công giáo ngày 13-04-2025",
    "desc": "CHÚA NHẬT LỄ LÁ. TƯỞNG NIỆM CUỘC THƯƠNG KHÓ CỦA CHÚA GIÊSU. Thánh vịnh tuần II",
    "read": "Lc 19,28-40. Thánh lễ: Is 50,4-7 ; Pl 2,6-11 ; Lc 22,14–23,56 (hay Lc 23,1-49)",
    "paole": "Áo Lễ Linh Mục: Đỏ"
  },
  {
    "date": "14-04-2025",
    "title": "Lịch công giáo ngày 14-04-2025",
    "desc": "THỨ HAI TUẦN THÁNH",
    "read": "Is 42,1-7 ; Ga 12,1-11 (Tm)",
    "paole": "Áo Lễ Linh Mục: Tím"
  },
  {
    "date": "15-04-2025",
    "title": "Lịch công giáo ngày 15-04-2025",
    "desc": "THỨ BA TUẦN THÁNH",
    "read": "Is 49,1-6 ; Ga 13,21-33.36-38 (Tm)",
    "paole": "Áo Lễ Linh Mục: Tím"
  },
  {
    "date": "16-04-2025",
    "title": "Lịch công giáo ngày 16-04-2025",
    "desc": "THỨ TƯ TUẦN THÁNH",
    "read": "Is 50,4-9a ; Mt 26,14-25 (Tm)",
    "paole": "Áo Lễ Linh Mục: Tím"
  },
  {
    "date": "17-04-2025",
    "title": "Lịch công giáo ngày 17-04-2025",
    "desc": "THỨ NĂM TUẦN THÁNH. Thánh lễ sáng: THÁNH LỄ LÀM PHÉP DẦU. Thánh lễ chiều: THÁNH LỄ TIỆC LY",
    "read": "Lễ sáng: Is 61,1-3a.6a.8b-9 ; Kh 1,5-8 ; Lc 4, 16-21. Lễ chiều: Xh 12,1-8.11-14 ; 1 Cr 11,23-26 ; Ga 13,1-15 (Tr)",
    "paole": "Áo Lễ Linh Mục: Trắng"
  },
  {
    "date": "18-04-2025",
    "title": "Lịch công giáo ngày 18-04-2025",
    "desc": "THỨ SÁU TUẦN THÁNH. TƯỞNG NIỆM CUỘC THƯƠNG KHÓ CỦA CHÚA GIÊSU. Buộc giữ chay và kiêng thịt",
    "read": "Lễ sáng: Is 61,1-3a.6a.8b-9 ; Kh 1,5-8 ; Lc 4, 16-21. Lễ chiều: Xh 12,1-8.11-14 ; 1 Cr 11,23-26 ; Ga 13,1-15 (Tr)",
    "paole": "Áo Lễ Linh Mục: Tím"
  },
  {
    "date": "19-04-2025",
    "title": "Lịch công giáo ngày 19-04-2025",
    "desc": "THỨ BẢY TUẦN THÁNH",
    "read": "Is 52,13–53,12 ; Dt 4,14-16 ; 5,7-9 ; Ga 18,1–19,42 (Đ)",
    "paole": "Áo Lễ Linh Mục: Đỏ"
  },
  {
    "date": "20-04-2025",
    "title": "Lịch công giáo ngày 20-04-2025",
    "desc": "CHÚA NHẬT PHỤC SINH. MỪNG CHÚA GIÊSU SỐNG LẠI",
    "read": "Canh thức Vượt Qua: 1) St 1,1–2,2 (hay St 1,1.26-31a) 2) St 22,1-18 (hay St 22,1-2.9a.10-13.15-18) 3) Xh 14,15–15,1a. 4) Is 54,5-14. 5) Is 55,1-11. 6) Br 3,9-15.32–4,4. 7) Ed 36,16-17a.18-28. 8) Rm 6,3-11. 9) Lc 24,1-12. Chính ngày: THÁNH LỄ CHÚA NHẬT PHỤC SINH. Cv 10,34a.37-43 ; Cl 3,1-4 (hay 1 Cr 5,6b-8) ; Ga 20,1-9 (hay Mc 16,1-8). (Thánh lễ chiều có thể đọc: Lc 24,13-35). (Tr)",
    "paole": "Áo Lễ Linh Mục: Trắng"
  },
  {
    "date": "21-04-2025",
    "title": "Lịch công giáo ngày 21-04-2025",
    "desc": "Tuần Bát Nhật Phục Sinh",
    "read": "Cv 2,14.22-32 ; Mt 28,8-15 (Tr)",
    "paole": "Áo Lễ Linh Mục: Trắng"
  },
  {
    "date": "22-04-2025",
    "title": "Lịch công giáo ngày 22-04-2025",
    "desc": "Tuần Bát Nhật Phục Sinh",
    "read": "",
    "paole": "Áo Lễ Linh Mục: Trắng"
  },
  {
    "date": "23-04-2025",
    "title": "Lịch công giáo ngày 23-04-2025",
    "desc": "Tuần Bát Nhật Phục Sinh",
    "read": "Cv 3,1-10 ; Lc 24,13-35 (Tr)",
    "paole": "Áo Lễ Linh Mục: Trắng"
  },
  {
    "date": "24-04-2025",
    "title": "Lịch công giáo ngày 24-04-2025",
    "desc": "Tuần Bát Nhật Phục Sinh",
    "read": "Cv 3,11-26 ; Lc 24,35-48 (Tr)",
    "paole": "Áo Lễ Linh Mục: Trắng"
  },
  {
    "date": "25-04-2025",
    "title": "Lịch công giáo ngày 25-04-2025",
    "desc": "Tuần Bát Nhật Phục Sinh",
    "read": "Cv 4,1-12 ; Ga 21,1-14 (Tr)",
    "paole": "Áo Lễ Linh Mục: Trắng"
  },
  {
    "date": "26-04-2025",
    "title": "Lịch công giáo ngày 26-04-2025",
    "desc": "Tuần Bát Nhật Phục Sinh",
    "read": "Cv 4,13-21 ; Mc 16,9-15 (Tr)",
    "paole": "Áo Lễ Linh Mục: Trắng"
  },
  {
    "date": "27-04-2025",
    "title": "Lịch công giáo ngày 27-04-2025",
    "desc": "CHÚA NHẬT II PHỤC SINH. CHÚA NHẬT VỀ LÒNG THƯƠNG XÓT CỦA THIÊN CHÚA",
    "read": "Cv 5,12-16 ; Kh 1,9-11a.12-13.17-19 ; Ga 20,19-31 (Tr)",
    "paole": "Áo Lễ Linh Mục: Trắng"
  },
  {
    "date": "28-04-2025",
    "title": "Lịch công giáo ngày 28-04-2025",
    "desc": "Thánh vịnh tuần II. Thánh Phêrô Chanel, linh mục, tử đạo. Thánh Luy Grignion Montfort, linh mục. Thánh Phaolô Phạm Khắc Khoan, linh mục. Thánh Phêrô Nguyễn Văn Hiếu và thánh Gioan Baotixita Đinh Văn Thành, thầy giảng, tử đạo (1840)",
    "read": "Cv 4,23-31 ; Ga 3,1-8 (Tr)",
    "paole": "Áo Lễ Linh Mục: Trắng"
  },
  {
    "date": "29-04-2025",
    "title": "Lịch công giáo ngày 29-04-2025",
    "desc": "Thánh Catarina Siêna, trinh nữ, tiến sĩ Hội Thánh",
    "read": "Cv 4,32-37 ; Ga 3,7b-15. (Tr)",
    "paole": "Áo Lễ Linh Mục: Trắng"
  },
  {
    "date": "30-04-2025",
    "title": "Lịch công giáo ngày 30-04-2025",
    "desc": "Thánh Piô V, Giáo hoàng",
    "read": "Cv 5,17-26 ; Ga 3,16-21 (Tr)",
    "paole": "Áo Lễ Linh Mục: Trắng"
  },
  {
    "date": "01-05-2025",
    "title": "Lịch công giáo ngày 01-05-2025",
    "desc": "Thánh Giuse Thợ",
    "read": "St 1,26–2,3 hay Cl 3,14-15.17.23-24 ; Mt 13,54-58 (Tr)",
    "paole": "Áo Lễ Linh Mục: Trắng"
  },
  {
    "date": "02-05-2025",
    "title": "Lịch công giáo ngày 02-05-2025",
    "desc": "Thánh Athanasiô, giám mục, tiến sĩ Hội Thánh.",
    "read": "Cv 5,34-42 ; Ga 6,1-15 (Tr)",
    "paole": "Áo Lễ Linh Mục: Trắng"
  },
  {
    "date": "03-05-2025",
    "title": "Lịch công giáo ngày 03-05-2025",
    "desc": "THÁNH PHILIPPHÊ VÀ THÁNH GIACÔBÊ, TÔNG ĐỒ",
    "read": "1 Cr 15,1-8 ; Ga 14,6-14 (Đ)",
    "paole": "Áo Lễ Linh Mục: Đỏ"
  },
  {
    "date": "04-05-2025",
    "title": "Lịch công giáo ngày 04-05-2025",
    "desc": "CHÚA NHẬT III PHỤC SINH. Thánh Vịnh Tuần III",
    "read": "Cv 5,27-32.40b-41 ; Kh 5,11-14 ; Ga 21,1-19 (hay Ga 21,1-14) (Tr)",
    "paole": "Áo Lễ Linh Mục: Trắng"
  },
  {
    "date": "05-05-2025",
    "title": "Lịch công giáo ngày 05-05-2025",
    "desc": "Thứ Hai trong tuần thứ Ba Mùa Phục Sinh",
    "read": "Cv 6,8-15 ; Ga 6,22-29 (Tr)",
    "paole": "Áo Lễ Linh Mục: Trắng"
  },
  {
    "date": "06-05-2025",
    "title": "Lịch công giáo ngày 06-05-2025",
    "desc": "Thứ Ba trong tuần thứ Ba Mùa Phục Sinh",
    "read": "Cv 7,51–8,1a; Ga 6,30-35 (Tr)",
    "paole": "Áo Lễ Linh Mục: Trắng"
  },
  {
    "date": "07-05-2025",
    "title": "Lịch công giáo ngày 07-05-2025",
    "desc": "Thứ Tư trong tuần thứ Ba Mùa Phục Sinh",
    "read": "Cv 8,1b-8 ; Ga 6,35-40 (Tr)",
    "paole": "Áo Lễ Linh Mục: Trắng"
  },
  {
    "date": "08-05-2025",
    "title": "Lịch công giáo ngày 08-05-2025",
    "desc": "Thứ Năm trong tuần thứ Ba Mùa Phục Sinh",
    "read": "Cv 8,26-40 ; Ga 6,44-51 (Tr)",
    "paole": "Áo Lễ Linh Mục: Trắng"
  },
  {
    "date": "09-05-2025",
    "title": "Lịch công giáo ngày 09-05-2025",
    "desc": "Thánh Gioan I, giáo hoàng, tử đạo. Thánh Giuse Ngô Duy Hiển, linh mục, tử đạo († 1840)",
    "read": "Cv 9,1-20 ; Ga 6,52-59 (Tr)",
    "paole": "Áo Lễ Linh Mục: Trắng"
  },
  {
    "date": "10-05-2025",
    "title": "Lịch công giáo ngày 10-05-2025",
    "desc": "Thánh Gioan Avila, linh mục, tiến sĩ Hội Thánh",
    "read": "Cv 9,31-42 ; Ga 6,51.60-69 (Tr)",
    "paole": "Áo Lễ Linh Mục: Trắng"
  },
  {
    "date": "11-05-2025",
    "title": "Lịch công giáo ngày 11-05-2025",
    "desc": "CHÚA NHẬT IV PHỤC SINH. Thánh vịnh tuần IV. CHÚA NHẬT CHÚA CHIÊN LÀNH. Cầu cho ơn thiên triệu linh mục và tu sĩ",
    "read": "Cv 13,14.43-52 ; Kh 7,9.14b-17 ; Ga 10,27-30 (Tr)",
    "paole": "Áo Lễ Linh Mục: Trắng"
  },
  {
    "date": "12-05-2025",
    "title": "Lịch công giáo ngày 12-05-2025",
    "desc": "Thánh Nêrêô và thánh Achilêô, tử đạo. Thánh Pancratiô, tử đạo",
    "read": "Cv 11,1-18 ; Ga 10,1-10 (Tr)",
    "paole": "Áo Lễ Linh Mục: Trắng"
  },
  {
    "date": "13-05-2025",
    "title": "Lịch công giáo ngày 13-05-2025",
    "desc": "Đức Mẹ Fatima",
    "read": "Cv 11,19-26 ; Ga 10,22-30. Lễ Đức Mẹ: Is 61,9-11 ; Lc 11,27-28 (Tr)",
    "paole": "Áo Lễ Linh Mục: Trắng"
  },
  {
    "date": "14-05-2025",
    "title": "Lịch công giáo ngày 14-05-2025",
    "desc": "THÁNH MATTHIA, TÔNG ĐỒ",
    "read": "Cv 1,15-17.20-26 ; Ga 15,9-17 (Đ)",
    "paole": "Áo Lễ Linh Mục: Đỏ"
  },
  {
    "date": "15-05-2025",
    "title": "Lịch công giáo ngày 15-05-2025",
    "desc": "Thứ Năm trong tuần thứ Tư Mùa Phục Sinh",
    "read": "Cv 13,13-25 ; Ga 13,16-20 (Tr)",
    "paole": "Áo Lễ Linh Mục: Trắng"
  },
  {
    "date": "16-05-2025",
    "title": "Lịch công giáo ngày 16-05-2025",
    "desc": "Thứ Sáu trong tuần thứ Tư Mùa Phục Sinh",
    "read": "Cv 13,26-33 ; Ga 14,1-6 (Tr)",
    "paole": "Áo Lễ Linh Mục: Trắng"
  },
  {
    "date": "17-05-2025",
    "title": "Lịch công giáo ngày 17-05-2025",
    "desc": "Thứ Bảy trong tuần thứ Tư Mùa Phục Sinh",
    "read": "Cv 13, 44-52 ; Ga 14,7-14 (Tr)",
    "paole": "Áo Lễ Linh Mục: Trắng"
  },
  {
    "date": "18-05-2025",
    "title": "Lịch công giáo ngày 18-05-2025",
    "desc": "CHÚA NHẬT V PHỤC SINH. Thánh Vịnh Tuần I",
    "read": "Cv 14,21b-27 ; Kh 21,1-5a ; Ga 13,31-33a.34-35 (Tr)",
    "paole": "Áo Lễ Linh Mục: Trắng"
  },
  {
    "date": "19-05-2025",
    "title": "Lịch công giáo ngày 19-05-2025",
    "desc": "Thứ Hai trong tuần thứ Năm Mùa Phục Sinh",
    "read": "Cv 14,5-18 ; Ga 14,21-26 (Tr)",
    "paole": "Áo Lễ Linh Mục: Trắng"
  },
  {
    "date": "20-05-2025",
    "title": "Lịch công giáo ngày 20-05-2025",
    "desc": "Thánh Bernarđinô Siêna, linh mục",
    "read": "Cv 14,19-28 ; Ga 14,27-31a (Tr)",
    "paole": "Áo Lễ Linh Mục: Trắng"
  },
  {
    "date": "21-05-2025",
    "title": "Lịch công giáo ngày 21-05-2025",
    "desc": "Thánh Christôphôrô Magalla-nes, linh mục và các bạn, tử đạo",
    "read": "Cv 15,1-6 ; Ga 15,1-8 ()",
    "paole": "Áo Lễ Linh Mục: Trắng"
  },
  {
    "date": "22-05-2025",
    "title": "Lịch công giáo ngày 22-05-2025",
    "desc": "Thánh Rita Cascia, nữ tu. Thánh Micae Hồ Đình Hy, quan thái bộc, tử đạo († 1857); thánh Laurensô Phạm Viết Ngôn, giáo dân, tử đạo († 1862)",
    "read": "Cv 15,7-21 ; Ga 15,9-11 (Tr)",
    "paole": "Áo Lễ Linh Mục: Trắng"
  },
  {
    "date": "23-05-2025",
    "title": "Lịch công giáo ngày 23-05-2025",
    "desc": "Thứ Sáu trong tuần thứ Năm Mùa Phục Sinh",
    "read": "Cv 15,22-31 ; Ga 15,12-17 (Tr)",
    "paole": "Áo Lễ Linh Mục: Trắng"
  },
  {
    "date": "24-05-2025",
    "title": "Lịch công giáo ngày 24-05-2025",
    "desc": "Thứ Bảy trong tuần thứ Năm Mùa Phục Sinh",
    "read": "Cv 16,1-10 ; Ga 15,18-21 (Tr)",
    "paole": "Áo Lễ Linh Mục: Trắng"
  },
  {
    "date": "25-05-2025",
    "title": "Lịch công giáo ngày 25-05-2025",
    "desc": "CHÚA NHẬT VI PHỤC SINH. Thánh Vịnh Tuần II",
    "read": "Cv 15,1-2.22-29 ; Kh 21,10-14.22-23 ; Ga 14,23-29 (Tr)",
    "paole": "Áo Lễ Linh Mục: Trắng"
  },
  {
    "date": "26-05-2025",
    "title": "Lịch công giáo ngày 26-05-2025",
    "desc": "Thánh Philipphê Nêri, linh mục.",
    "read": "Cv 16,11-15 ; Ga 15,26–16,4a (Tr)",
    "paole": "Áo Lễ Linh Mục: Trắng"
  },
  {
    "date": "27-05-2025",
    "title": "Lịch công giáo ngày 27-05-2025",
    "desc": "Thánh Augustinô Cantuariô, giám mục",
    "read": "Cv 16,22-34 ; Ga 16,5-11 (Tr)",
    "paole": "Áo Lễ Linh Mục: Trắng"
  },
  {
    "date": "28-05-2025",
    "title": "Lịch công giáo ngày 28-05-2025",
    "desc": "Thánh Phaolô Trần Văn Hạnh, giáo dân, tử đạo († 1859). Chiều: LỄ VỌNG CHÚA GIÊSU LÊN TRỜI",
    "read": "Cv 17,15.22–18,1 ; Ga 16,12-15. Lễ vọng: bài đọc chính ngày lễ (Tr)",
    "paole": "Áo Lễ Linh Mục: Trắng"
  },
  {
    "date": "29-05-2025",
    "title": "Lịch công giáo ngày 29-05-2025",
    "desc": "CHÚA GIÊSU LÊN TRỜI",
    "read": "Cv 1,1-11 ; Dt 9,24-28 ; 10,19-23 ; (hay Ep 1,17-23) ; Lc 24,46-53 (Tr)",
    "paole": "Áo Lễ Linh Mục: Trắng"
  },
  {
    "date": "30-05-2025",
    "title": "Lịch công giáo ngày 30-05-2025",
    "desc": "Thứ Sáu trong tuần thứ Sáu Mùa Phục Sinh",
    "read": "Cv 18,9-18 ; Ga 16,20-23a (Tr)",
    "paole": "Áo Lễ Linh Mục: Trắng"
  },
  {
    "date": "31-05-2025",
    "title": "Lịch công giáo ngày 31-05-2025",
    "desc": "ĐỨC MARIA THĂM VIẾNG BÀ ÊLISABETH",
    "read": "Xp 3,14-18a (hay Rm 12,9-16b) ; Lc 1,39-56 (Tr)",
    "paole": "Áo Lễ Linh Mục: Trắng"
  },
  {
    "date": "01-06-2025",
    "title": "Lịch công giáo ngày 01-06-2025",
    "desc": "CHÚA NHẬT VII PHỤC SINH. Thánh Vịnh Tuần III",
    "read": "Cv 7,55-60 ; Kh 22,12-14.16-17.20 ; Ga 17,20-26 (Tr)",
    "paole": "Áo Lễ Linh Mục: Trắng"
  },
  {
    "date": "02-06-2025",
    "title": "Lịch công giáo ngày 02-06-2025",
    "desc": "Thánh Marcellinô và thánh Phêrô, tử đạo. Thánh Đaminh Trần Duy Ninh, giáo dân, tử đạo († 1862)",
    "read": "Cv 19,1-8 ; Ga 16,29-33 (Tr)",
    "paole": "Áo Lễ Linh Mục: Trắng"
  },
  {
    "date": "03-06-2025",
    "title": "Lịch công giáo ngày 03-06-2025",
    "desc": "Thánh Carôlô Lwanga và các bạn, tử đạo.",
    "read": "Cv 20,17-27 ; Ga 17,1-11a (Đ)",
    "paole": "Áo Lễ Linh Mục: Trắng"
  },
  {
    "date": "04-06-2025",
    "title": "Lịch công giáo ngày 04-06-2025",
    "desc": "Thánh Phêrô Vêrôna, linh mục, tử đạo",
    "read": "Cv 20,28-38 ; Ga 17,11b-19 (Tr)",
    "paole": "Áo Lễ Linh Mục: Trắng"
  },
  {
    "date": "05-06-2025",
    "title": "Lịch công giáo ngày 05-06-2025",
    "desc": "Thánh Bônifatiô, giám mục, tử đạo, Thánh Luca Vũ Bá Loan, linh mục († 1840); thánh Đaminh Trần Văn Toại (Toái), ngư phủ; thánh Đaminh Nguyễn Văn Huyên (Huyện), ngư phủ, tử đạo († 1862)",
    "read": "Cv 22,30 ; 23,6-11 ; Ga 17,20-26 (Đ)",
    "paole": "Áo Lễ Linh Mục: Đỏ"
  },
  {
    "date": "06-06-2025",
    "title": "Lịch công giáo ngày 06-06-2025",
    "desc": "Thánh Norbertô, giám mục. Thánh Phêrô Đinh Văn Dũng, ngư phủ; thánh Phêrô Đinh Văn Thuần, ngư phủ; thánh Vinh Sơn Phạm Văn Dương, thu thuế, tử đạo († 1862)",
    "read": "Cv 25,13b-21 ; Ga 21,15-19 (Tr)",
    "paole": "Áo Lễ Linh Mục: Trắng"
  },
  {
    "date": "07-06-2025",
    "title": "Lịch công giáo ngày 07-06-2025",
    "desc": "Thánh Giuse Trần Văn Tuấn, nông dân, tử đạo († 1862). Ban chiều: LỄ VỌNG CHÚA THÁNH THẦN HIỆN XUỐNG (Đ)",
    "read": "Ban sáng: Cv 28,16-20.30-31 ; Ga 21,20-25. St 11,1-9 (hay Xh 19,3-8a.16-20b hay Ed 37,1-14 hay Ge 3,1-5) ; Rm 8,22-27 ; Ga 7,37-39 (Tr)",
    "paole": "Áo Lễ Linh Mục: Trắng"
  },
  {
    "date": "08-06-2025",
    "title": "Lịch công giáo ngày 08-06-2025",
    "desc": "CHÚA THÁNH THẦN HIỆN XUỐNG",
    "read": "Cv 2,1-11 ; 1 Cr 12,3b-7.12-13 (hay Rm 8,8-17) ; Ga 20,19-23 (hay Ga 14,15-16.23b-26) (Đ)",
    "paole": "Áo Lễ Linh Mục: Đỏ"
  },
  {
    "date": "09-06-2025",
    "title": "Lịch công giáo ngày 09-06-2025",
    "desc": "Tuần X Thường Niên. Thánh vịnh tuần II. Đức Trinh Nữ Maria, Mẹ Hội Thánh",
    "read": "St 3,9-15.20 (hay Cv 1,12-14) ; Ga 19,25-34 (Tr)",
    "paole": "Áo Lễ Linh Mục: Trắng"
  },
  {
    "date": "10-06-2025",
    "title": "Lịch công giáo ngày 10-06-2025",
    "desc": "Thứ Ba trong tuần thứ Mười Mùa Quanh Năm",
    "read": "2 Cr 1,18-22 ; Mt 5,13-16 (X)",
    "paole": "Áo Lễ Linh Mục: Trắng"
  },
  {
    "date": "11-06-2025",
    "title": "Lịch công giáo ngày 11-06-2025",
    "desc": "THÁNH BARNABA, TÔNG ĐỒ",
    "read": "Cv 11,21b-26 ; 13,1-3 ; Mt 10,6-13 (Đ)",
    "paole": "Áo Lễ Linh Mục: Đỏ"
  },
  {
    "date": "12-06-2025",
    "title": "Lịch công giáo ngày 12-06-2025",
    "desc": "Thứ Năm trong tuần thứ Mười Mùa Quanh Năm",
    "read": "2 Cr 3,15–4,1.3-6 ; Mt 5,20-26 (X)",
    "paole": "Áo Lễ Linh Mục: Xanh"
  },
  {
    "date": "13-06-2025",
    "title": "Lịch công giáo ngày 13-06-2025",
    "desc": "Thánh Antôn Pađôva, linh mục, tiến sĩ Hội Thánh",
    "read": "2 Cr 4,7-15 ; Mt 5,27-32 (Tr)",
    "paole": "Áo Lễ Linh Mục: Trắng"
  },
  {
    "date": "14-06-2025",
    "title": "Lịch công giáo ngày 14-06-2025",
    "desc": "Thứ Bảy trong tuần thứ Mười Mùa Quanh Năm",
    "read": "2 Cr 5,14-21 ; Mt 5,33-37 (X)",
    "paole": "Áo Lễ Linh Mục: Xanh"
  },
  {
    "date": "15-06-2025",
    "title": "Lịch công giáo ngày 15-06-2025",
    "desc": "LỄ CHÚA BA NGÔI",
    "read": "Cn 8,22-31 ; Rm 5,1-5 ; Ga 16,12-15 (Tr)",
    "paole": "Áo Lễ Linh Mục: Trắng"
  },
  {
    "date": "16-06-2025",
    "title": "Lịch công giáo ngày 16-06-2025",
    "desc": "Thánh vịnh tuần III. Thánh Đaminh Nguyễn Huy Nguyên, chánh trương; thánh Đaminh Nguyễn Đức Nhi, giáo dân; thánh Đaminh Nguyễn Đức Mạo, giáo dân; thánh Vinh Sơn Nguyễn Mạnh Tương, chánh tổng; thánh Anrê Nguyễn Mạnh Tường, giáo dân, tử đạo († 1862)",
    "read": "2 Cr 6,1-10 ; Mt 5,38-42 (X)",
    "paole": "Áo Lễ Linh Mục: Xanh"
  },
  {
    "date": "17-06-2025",
    "title": "Lịch công giáo ngày 17-06-2025",
    "desc": "Thánh Phêrô Phan Hữu Đa, thợ mộc, tử đạo († 1862)",
    "read": "2 Cr 8,1-9 ; Mt 5,43-48 (X)",
    "paole": "Áo Lễ Linh Mục: Xanh"
  },
  {
    "date": "18-06-2025",
    "title": "Lịch công giáo ngày 18-06-2025",
    "desc": "Thứ Tư trong tuần thứ Mười Một Mùa Quanh Năm",
    "read": "2 Cr 9,6-11 ; Mt 6,1-6.16-18 (X)",
    "paole": "Áo Lễ Linh Mục: Xanh"
  },
  {
    "date": "19-06-2025",
    "title": "Lịch công giáo ngày 19-06-2025",
    "desc": "Thánh Rômualđô, viện phụ",
    "read": "2 Cr 11,1-11 ; Mt 6,7-15 (X)",
    "paole": "Áo Lễ Linh Mục: Xanh"
  },
  {
    "date": "20-06-2025",
    "title": "Lịch công giáo ngày 20-06-2025",
    "desc": "Thứ Sáu trong tuần thứ Mười Một Mùa Quanh Năm",
    "read": "2 Cr 11,18.21b-30 ; Mt 6,19-23 (X)",
    "paole": "Áo Lễ Linh Mục: Xanh"
  },
  {
    "date": "21-06-2025",
    "title": "Lịch công giáo ngày 21-06-2025",
    "desc": "Thánh Luy Gônzaga, tu sĩ",
    "read": "2 Cr 12,1-10 ; Mt 6,24-34 (Tr)",
    "paole": "Áo Lễ Linh Mục: Trắng"
  },
  {
    "date": "22-06-2025",
    "title": "Lịch công giáo ngày 22-06-2025",
    "desc": "MÌNH VÀ MÁU THÁNH CHÚA KITÔ",
    "read": "St 14,18-20 ; 1 Cr 11, 23-26 ; Lc 9, 11b-17 (Tr)",
    "paole": "Áo Lễ Linh Mục: Trắng"
  },
  {
    "date": "23-06-2025",
    "title": "Lịch công giáo ngày 23-06-2025",
    "desc": "Thánh vịnh tuần IV. Ban chiều: LỄ VỌNG SINH NHẬT THÁNH GIOAN TẨY GIẢ (Tr)",
    "read": "Ban sáng: St 12,1-9 ; Mt 7,1-5. Ban chiều: Gr 1,4-10 ; 1 Pr 1,8-12 ; Lc 1,5-17 (X)",
    "paole": "Áo Lễ Linh Mục: Xanh"
  },
  {
    "date": "24-06-2025",
    "title": "Lịch công giáo ngày 24-06-2025",
    "desc": "SINH NHẬT THÁNH GIOAN TẨY GIẢ",
    "read": "Is 49,1-6 ; Cv 13,22-26 ; Lc 1,57-66.80 (Tr)",
    "paole": "Áo Lễ Linh Mục: Trắng"
  },
  {
    "date": "25-06-2025",
    "title": "Lịch công giáo ngày 25-06-2025",
    "desc": "Thứ Tư trong tuần thứ Mười Hai Mùa Quanh Năm",
    "read": "St 15,1-12.17-18 ; Mt 7,15-20 (X)",
    "paole": "Áo Lễ Linh Mục: Xanh"
  },
  {
    "date": "26-06-2025",
    "title": "Lịch công giáo ngày 26-06-2025",
    "desc": "Thánh Dumingo Henares Minh, giám mục, tử đạo. Thánh Phanxicô Xaviê Đỗ Văn Chiểu, thầy giảng, tử đạo († 1838)",
    "read": "St 16,1-12.15-16 ; Mt 7,21-29 (X)",
    "paole": "Áo Lễ Linh Mục: Xanh"
  },
  {
    "date": "27-06-2025",
    "title": "Lịch công giáo ngày 27-06-2025",
    "desc": "THÁNH TÂM CHÚA GIÊSU",
    "read": "Ed 34,11-16 ; Rm 5,5b-11 ; Lc 15,3-7 ()",
    "paole": "Áo Lễ Linh Mục: Trắng"
  },
  {
    "date": "28-06-2025",
    "title": "Lịch công giáo ngày 28-06-2025",
    "desc": "Trái Tim Vô Nhiễm Nguyên Tội Đức Trinh Nữ Maria. Ban chiều: LỄ VỌNG THÁNH PHÊRÔ VÀ THÁNH PHAOLÔ, TÔNG ĐỒ (Đ)",
    "read": "Ban sáng: Is 61,9-11 ; Lc 2,41-51. Ban chiều: Cv 3,1-10 ; GI 1,11-20 ; Ga 21,15-19 (Tr)",
    "paole": "Áo Lễ Linh Mục: Đỏ"
  },
  {
    "date": "29-06-2025",
    "title": "Lịch công giáo ngày 29-06-2025",
    "desc": "THÁNH PHÊRÔ VÀ THÁNH PHAOLÔ, TÔNG ĐỒ",
    "read": "Cv 12,1-11 ; 2 Tm 4,6-8.17-18 ; Mt 16,13-19 (Đ)",
    "paole": "Áo Lễ Linh Mục: Đỏ"
  },
  {
    "date": "30-06-2025",
    "title": "Lịch công giáo ngày 30-06-2025",
    "desc": "Các thánh tử đạo tiên khởi của giáo đoàn Rôma. Thánh Vinh Sơn Đỗ Yến, linh mục, tử đạo († 1838)",
    "read": "St 18,16-33 ; Mt 8,18-22 (Đ)",
    "paole": "Áo Lễ Linh Mục: Đỏ"
  },
  {
    "date": "01-07-2025",
    "title": "Lịch công giáo ngày 01-07-2025",
    "desc": "Thứ Ba trong tuần thứ Mười Ba Mùa Quanh Năm",
    "read": "St 19,15-29 ; Mt 8,23-27 (X)",
    "paole": "Áo Lễ Linh Mục: Xanh"
  },
  {
    "date": "02-07-2025",
    "title": "Lịch công giáo ngày 02-07-2025",
    "desc": "Thứ Tư trong tuần thứ Mười Ba Mùa Quanh Năm",
    "read": "St 21,5.8-20 ; Mt 8,28-34 (X)",
    "paole": "Áo Lễ Linh Mục: Xanh"
  },
  {
    "date": "03-07-2025",
    "title": "Lịch công giáo ngày 03-07-2025",
    "desc": "THÁNH TÔMA, TÔNG ĐỒ",
    "read": "Ep 2,19-22 ; Ga 20,24-29 (Đ)",
    "paole": "Áo Lễ Linh Mục: Đỏ"
  },
  {
    "date": "04-07-2025",
    "title": "Lịch công giáo ngày 04-07-2025",
    "desc": "Thánh nữ Êlisabeth Bồ Đào Nha. Thánh Giuse Nguyễn Đình Uyển, thầy giảng, tử đạo († 1838)",
    "read": "St 23,1-4.19 ; 24,1-8.62-67 ; Mt 9,9-13 (X)",
    "paole": "Áo Lễ Linh Mục: Xanh"
  },
  {
    "date": "05-07-2025",
    "title": "Lịch công giáo ngày 05-07-2025",
    "desc": "Thánh Antôn Maria Zaccaria, linh mục",
    "read": "St 27,1-5.15-29 . Mt 9,14-17 (X)",
    "paole": "Áo Lễ Linh Mục: Xanh"
  },
  {
    "date": "06-07-2025",
    "title": "Lịch công giáo ngày 06-07-2025",
    "desc": "Chúa Nhật thứ Mười Bốn Mùa Quanh Năm",
    "read": "Is 66,10-14c ; Gl 6,14-18 ; Lc 10,1-12. 17-20 (hay Lc 10,1-9) (X)",
    "paole": "Áo Lễ Linh Mục: Xanh"
  },
  {
    "date": "07-07-2025",
    "title": "Lịch công giáo ngày 07-07-2025",
    "desc": "Thứ Hai trong tuần thứ Mười Bốn Mùa Quanh Năm",
    "read": "St 28,10-22a ; Mt 9,18-26 (X)",
    "paole": "Áo Lễ Linh Mục: Xanh"
  },
  {
    "date": "08-07-2025",
    "title": "Lịch công giáo ngày 08-07-2025",
    "desc": "Thứ Ba trong tuần thứ Mười Bốn Mùa Quanh Năm",
    "read": "St 32,22-32 ; Mt 9,32-38 (X)",
    "paole": "Áo Lễ Linh Mục: Xanh"
  },
  {
    "date": "09-07-2025",
    "title": "Lịch công giáo ngày 09-07-2025",
    "desc": "Thánh Augustinô Zhao Rong, linh mục và các bạn, tử đạo",
    "read": "St 41,55-57 ; 42,5-7.17-24a ; Mt 10,1-7 (X)",
    "paole": "Áo Lễ Linh Mục: Xanh"
  },
  {
    "date": "10-07-2025",
    "title": "Lịch công giáo ngày 10-07-2025",
    "desc": "Thánh Phêrô Nguyễn Khắc Tự, thầy giảng. Thánh Antôn Nguyễn Hữu Quỳnh (Năm Quỳnh), trùm họ, tử đạo († 1840)",
    "read": "St 44,18-21.23b-29 ; 45,1-5 ; Mt 10,7-15 (X)",
    "paole": "Áo Lễ Linh Mục: Xanh"
  },
  {
    "date": "11-07-2025",
    "title": "Lịch công giáo ngày 11-07-2025",
    "desc": "Thánh Bênêđictô, viện phụ",
    "read": "St 46,1-7.28-30 ; Mt 10,16-23 (Tr)",
    "paole": "Áo Lễ Linh Mục: Trắng"
  },
  {
    "date": "12-07-2025",
    "title": "Lịch công giáo ngày 12-07-2025",
    "desc": "Thánh Ignacio Clemente Delgado Y, giám mục, tử đạo († 1838). Thánh Anê Lê Thị Thành (bà thánh Đê), giáo dân, tử đạo († 1841). Thánh Phêrô Hoàng Khanh, linh mục, tử đạo († 1842)",
    "read": "St 49,29-32 ; 50,15-26a ; Mt 10,24-33 (X)",
    "paole": "Áo Lễ Linh Mục: Xanh"
  },
  {
    "date": "13-07-2025",
    "title": "Lịch công giáo ngày 13-07-2025",
    "desc": "Chúa Nhật thứ Mười Lăm Mùa Quanh Năm",
    "read": "Đnl 30,10-14 ; Cl 1,15-20 ; Lc 10,25-37 (X)",
    "paole": "Áo Lễ Linh Mục: Xanh"
  },
  {
    "date": "14-07-2025",
    "title": "Lịch công giáo ngày 14-07-2025",
    "desc": "Thánh Camillô Lellis, linh mục",
    "read": "Xh 1,8-14.22 ; Mt 10,34–11,1 (X)",
    "paole": "Áo Lễ Linh Mục: Trắng"
  },
  {
    "date": "15-07-2025",
    "title": "Lịch công giáo ngày 15-07-2025",
    "desc": "Thánh Bônaventura, giám mục, tiến sĩ Hội Thánh",
    "read": "Xh 2,1-15a ; Mt 11,20-24 ()",
    "paole": "Áo Lễ Linh Mục: Trắng"
  },
  {
    "date": "16-07-2025",
    "title": "Lịch công giáo ngày 16-07-2025",
    "desc": "Đức Mẹ núi Carmêlô (Tr)",
    "read": "Xh 3,1-6.9-12 ; Mt 11,25-27. Lễ Đức Mẹ: Dcr 2,14-17; Mt 12,46-50 (X)",
    "paole": "Áo Lễ Linh Mục: Xanh"
  },
  {
    "date": "17-07-2025",
    "title": "Lịch công giáo ngày 17-07-2025",
    "desc": "Thứ Năm trong tuần thứ Mười Lăm Mùa Quanh Năm",
    "read": "Xh 3,13-20 ; Mt 11,28-30 (X)",
    "paole": "Áo Lễ Linh Mục: Xanh"
  },
  {
    "date": "18-07-2025",
    "title": "Lịch công giáo ngày 18-07-2025",
    "desc": "Thánh Đaminh Đinh Văn Đạo (Đạt), quân nhân, tử đạo († 1839)",
    "read": "Xh 11,10–12,14 ; Mt 12,1-8 (X)",
    "paole": "Áo Lễ Linh Mục: Xanh"
  },
  {
    "date": "19-07-2025",
    "title": "Lịch công giáo ngày 19-07-2025",
    "desc": "Thứ Bảy trong tuần thứ Mười Lăm Mùa Quanh Năm",
    "read": "Xh 12,37-42 ; Mt 12,14-21 (X)",
    "paole": "Áo Lễ Linh Mục: Xanh"
  },
  {
    "date": "20-07-2025",
    "title": "Lịch công giáo ngày 20-07-2025",
    "desc": "Chúa Nhật thứ Mười Sáu Mùa Quanh Năm",
    "read": "St 18,1-10a ; Cl 1,24-28 ; Lc 10,38-42 (X)",
    "paole": "Áo Lễ Linh Mục: Xanh"
  },
  {
    "date": "21-07-2025",
    "title": "Lịch công giáo ngày 21-07-2025",
    "desc": "Thánh Laurensô Brinđisi, linh mục",
    "read": "Xh 14,5-18 ; Mt 12,38-42 (X)",
    "paole": "Áo Lễ Linh Mục: Xanh"
  },
  {
    "date": "22-07-2025",
    "title": "Lịch công giáo ngày 22-07-2025",
    "desc": "THÁNH NỮ MARIA MAGĐA-LÊNA",
    "read": "Dc 3,1-4a (hay 2 Cr 5,14-17) ; Ga 20,1-2.11-18 (Tr)",
    "paole": "Áo Lễ Linh Mục: Trắng"
  },
  {
    "date": "23-07-2025",
    "title": "Lịch công giáo ngày 23-07-2025",
    "desc": "Thánh Birgitta, nữ tu",
    "read": "Xh 16,1-5.9-15 ; Mt 13,1-9 (X)",
    "paole": "Áo Lễ Linh Mục: Xanh"
  },
  {
    "date": "24-07-2025",
    "title": "Lịch công giáo ngày 24-07-2025",
    "desc": "Thánh Sarbêliô Makhluf, linh mục. Thánh José Fernandez Hiền, linh mục, tử đạo († 1838)",
    "read": "Xh 19,1-2.9-11.16-20b ; Mt 13,10-17 (X)",
    "paole": "Áo Lễ Linh Mục: Xanh"
  },
  {
    "date": "25-07-2025",
    "title": "Lịch công giáo ngày 25-07-2025",
    "desc": "THÁNH GIACÔBÊ, TÔNG ĐỒ",
    "read": "2 Cr 4,7-15 ; Mt 20,20-28 (Đ)",
    "paole": "Áo Lễ Linh Mục: Đỏ"
  },
  {
    "date": "26-07-2025",
    "title": "Lịch công giáo ngày 26-07-2025",
    "desc": "Thánh Joachim và thánh Anna, song thân Đức Maria.",
    "read": "Xh 24,3-8 ; Mt 13,24-30. Lễ hai thánh: Hc 44,1.10-15 ; Mt 13,16-17 (Tr)",
    "paole": "Áo Lễ Linh Mục: Trắng"
  },
  {
    "date": "27-07-2025",
    "title": "Lịch công giáo ngày 27-07-2025",
    "desc": "Chúa Nhật thứ Mười Bảy Mùa Quanh Năm",
    "read": "St 18,20-32 ; Cl 2,12-14 ; Lc 11,1-13 (X)",
    "paole": "Áo Lễ Linh Mục: Xanh"
  },
  {
    "date": "28-07-2025",
    "title": "Lịch công giáo ngày 28-07-2025",
    "desc": "Thánh Melchor Garcia Sampedro Xuyên, giám mục, tử đạo († 1858)",
    "read": "Xh 32,15-24.30-34 ; Mt 13,31-35 (X)",
    "paole": "Áo Lễ Linh Mục: Xanh"
  },
  {
    "date": "29-07-2025",
    "title": "Lịch công giáo ngày 29-07-2025",
    "desc": "Thánh nữ Martha, Maria và Ladarô",
    "read": "1 Ga 4,7-16 ; Ga 11,19-27 (hay Lc 10,38-42) (Tr)",
    "paole": "Áo Lễ Linh Mục: Trắng"
  },
  {
    "date": "30-07-2025",
    "title": "Lịch công giáo ngày 30-07-2025",
    "desc": "Thánh Phêrô Kim Ngôn, giám mục, tiến sĩ Hội Thánh",
    "read": "Xh 34,29-35 ; Mt 13,44-46 (X)",
    "paole": "Áo Lễ Linh Mục: Xanh"
  },
  {
    "date": "31-07-2025",
    "title": "Lịch công giáo ngày 31-07-2025",
    "desc": "Thánh Ignatiô Loyôla, linh mục",
    "read": "Xh 40,16-21.34-38 ; Mt 13,47-53 (Tr)",
    "paole": "Áo Lễ Linh Mục: Trắng"
  },
  {
    "date": "01-08-2025",
    "title": "Lịch công giáo ngày 01-08-2025",
    "desc": "Thánh Alphongsô Maria Ligôri, giám mục, tiến sĩ Hội Thánh",
    "read": "Lv 23,1.4-11.15-16.27.34b-37 ; Mt 13,54-58 (Tr)",
    "paole": "Áo Lễ Linh Mục: Trắng"
  },
  {
    "date": "02-08-2025",
    "title": "Lịch công giáo ngày 02-08-2025",
    "desc": "Thánh Êusêbiô Vercellêsi. Thánh Phêrô Julianô Eymard, linh mục",
    "read": "Lv 25,1.8-17 ; Mt 14.1-12 (X)",
    "paole": "Áo Lễ Linh Mục: Xanh"
  },
  {
    "date": "03-08-2025",
    "title": "Lịch công giáo ngày 03-08-2025",
    "desc": "CHÚA NHẬT XVIII THƯỜNG NIÊN. Thánh vịnh tuần II",
    "read": "Gv 1,2 ; 2,21-23 ; Cl 3,1-5.9-11 ; Lc 12,13-21 (X)",
    "paole": "Áo Lễ Linh Mục: Xanh"
  },
  {
    "date": "04-08-2025",
    "title": "Lịch công giáo ngày 04-08-2025",
    "desc": "Thánh Gioan Maria Vianney, linh mục",
    "read": "Ds 11,4b-15 ; Mt 14,13-21 (hay Mt 14,22-36) (Tr)",
    "paole": "Áo Lễ Linh Mục: Trắng"
  },
  {
    "date": "05-08-2025",
    "title": "Lịch công giáo ngày 05-08-2025",
    "desc": "Cung hiến thánh đường Đức Maria",
    "read": "Ds 12,1-13 ; Mt 14,22-36 (hay Mt 15,1-2.10-14). Lễ Đức Mẹ (Tr): Kh 21,1-5a ; Lc 11,27-28 (X)",
    "paole": "Áo Lễ Linh Mục: Xanh"
  },
  {
    "date": "06-08-2025",
    "title": "Lịch công giáo ngày 06-08-2025",
    "desc": "CHÚA HIỂN DUNG",
    "read": "Đn 7.9-10,13-14 (hay 2 Pr 1,16-19) ; Lc 9,28b-36 (Tr)",
    "paole": "Áo Lễ Linh Mục: Trắng"
  },
  {
    "date": "07-08-2025",
    "title": "Lịch công giáo ngày 07-08-2025",
    "desc": "Thánh Xystô II, giáo hoàng và các bạn, tử đạo. Thánh Cajêtanô, linh mục",
    "read": "Ds 20,1-13 ; Mt 16,13-23 (X)",
    "paole": "Áo Lễ Linh Mục: Xanh"
  },
  {
    "date": "08-08-2025",
    "title": "Lịch công giáo ngày 08-08-2025",
    "desc": "Thánh Đa Minh, linh mục",
    "read": "Đnl 4,32-40 ; Mt 16,24-28 (Tr)",
    "paole": "Áo Lễ Linh Mục: Trắng"
  },
  {
    "date": "09-08-2025",
    "title": "Lịch công giáo ngày 09-08-2025",
    "desc": "Thánh Têrêsa Bênêđicta Thánh Giá, nữ tu, tử đạo",
    "read": "Đnl 6,4-13 ; Mt 17,14-20 (X)",
    "paole": "Áo Lễ Linh Mục: Xanh"
  },
  {
    "date": "10-08-2025",
    "title": "Lịch công giáo ngày 10-08-2025",
    "desc": "CHÚA NHẬT XIX THƯỜNG NIÊN. Thánh vịnh tuần III",
    "read": "Kn 18,6-9 ; Dt 11,1-2.8-19 (hay Dt 11,1-2.8-12) ; Lc 12,32-48 (hay Lc 12,35-40) (X)",
    "paole": "Áo Lễ Linh Mục: Xanh"
  },
  {
    "date": "11-08-2025",
    "title": "Lịch công giáo ngày 11-08-2025",
    "desc": "Thánh Clara, trinh nữ",
    "read": "Đnl 10,12-22 ; Mt 17,22-27 (Tr)",
    "paole": "Áo Lễ Linh Mục: Trắng"
  },
  {
    "date": "12-08-2025",
    "title": "Lịch công giáo ngày 12-08-2025",
    "desc": "Thánh Joanna Phanxica Chantal, nữ tu. Thánh Giacôbê Đỗ Mai Năm, linh mục; thánh Antôn Nguyễn Tiến Đích, chánh trương; thánh Micae Nguyễn Huy Mỹ, lý trưởng, tử đạo († 1838)",
    "read": "Đnl 31,1-8 ; Mt 18,1-5.10.12-14 (X)",
    "paole": "Áo Lễ Linh Mục: Xanh"
  },
  {
    "date": "13-08-2025",
    "title": "Lịch công giáo ngày 13-08-2025",
    "desc": "Thánh Pontianô, giáo hoàng và thánh Hippôlytô, linh mục, tử đạo",
    "read": "Đnl 34,1-12 ; Mt 18,15-20 (X)",
    "paole": "Áo Lễ Linh Mục: Xanh"
  },
  {
    "date": "14-08-2025",
    "title": "Lịch công giáo ngày 14-08-2025",
    "desc": "Thánh Maximilianô Maria Kolbê, linh mục, tử đạo. Chiều: LỄ VỌNG ĐỨC MẸ LÊN TRỜI (Tr)",
    "read": "Gs 3,7-110a.11.13-17 ; Mt 18,21–19,1. Chiều: 1 Sb 15,3-4.15-16 ; 16,1-2 ; 1 Cr 15, 54b-57 ; Lc 11,27-28 (Đ)",
    "paole": "Áo Lễ Linh Mục: Đỏ"
  },
  {
    "date": "15-08-2025",
    "title": "Lịch công giáo ngày 15-08-2025",
    "desc": "ĐỨC MẸ LÊN TRỜI",
    "read": "Kh 11,19a ; 12,1-6a.10ab ; 1 Cr 15,20-27; Lc 1, 39-56 (Tr)",
    "paole": "Áo Lễ Linh Mục: Trắng"
  },
  {
    "date": "16-08-2025",
    "title": "Lịch công giáo ngày 16-08-2025",
    "desc": "Thánh Stêphanô, vua nước Hungari",
    "read": "Gs 24,14-29 ; Mt 19,13-15 (X)",
    "paole": "Áo Lễ Linh Mục: Xanh"
  },
  {
    "date": "17-08-2025",
    "title": "Lịch công giáo ngày 17-08-2025",
    "desc": "CHÚA NHẬT XX THƯỜNG NIÊN. Thánh vịnh tuần IV. Được cử hành lễ trọng (Tr): ĐỨC MẸ HỒN XÁC LÊN TRỜI",
    "read": "Gr 38,4-6.8-10 ; Dt 12,1-4 ; Lc 12,49-53. Lễ trọng: ngày chính lễ (X)",
    "paole": "Áo Lễ Linh Mục: Xanh"
  },
  {
    "date": "18-08-2025",
    "title": "Lịch công giáo ngày 18-08-2025",
    "desc": "Thứ Hai trong tuần thứ Hai Mươi Mùa Quanh Năm",
    "read": "Tl 2,11-19 ; Mt 19,16-22 (X)",
    "paole": "Áo Lễ Linh Mục: Xanh"
  },
  {
    "date": "19-08-2025",
    "title": "Lịch công giáo ngày 19-08-2025",
    "desc": "Thánh Gioan Êuđê, linh mục",
    "read": "Tl 6,11-24a ; Mt 19,23-30 (X)",
    "paole": "Áo Lễ Linh Mục: Xanh"
  },
  {
    "date": "20-08-2025",
    "title": "Lịch công giáo ngày 20-08-2025",
    "desc": "Thánh Bernarđô, viện phụ, tiến sĩ Hội Thánh",
    "read": "Tl 9,6-15 ; Mt 20,1-16a (Tr)",
    "paole": "Áo Lễ Linh Mục: Trắng"
  },
  {
    "date": "21-08-2025",
    "title": "Lịch công giáo ngày 21-08-2025",
    "desc": "Thánh Giuse Đặng Đình Viên, linh mục, tử đạo († 1838). Thánh Piô X, giáo hoàng (Tr)",
    "read": "Tl 11,29-39a ; Mt 22,1-14 (Đ)",
    "paole": "Áo Lễ Linh Mục: Đỏ"
  },
  {
    "date": "22-08-2025",
    "title": "Lịch công giáo ngày 22-08-2025",
    "desc": "Đức Maria Nữ Vương",
    "read": "Is 9,1-6 ; Lc 1,26-38 (Tr)",
    "paole": "Áo Lễ Linh Mục: Trắng"
  },
  {
    "date": "23-08-2025",
    "title": "Lịch công giáo ngày 23-08-2025",
    "desc": "Thánh Rôsa Lima, trinh nữ",
    "read": "R 2,1-3.8-11 ; 4,13-17 ; Mt 23,1-12 (X)",
    "paole": "Áo Lễ Linh Mục: Xanh"
  },
  {
    "date": "24-08-2025",
    "title": "Lịch công giáo ngày 24-08-2025",
    "desc": "CHÚA NHẬT XXI THƯỜNG NIÊN. Thánh vịnh tuần I",
    "read": "Is 66,18-21 ; Dt 12,5-7.11-13 ; Lc 13,22-30 (X)",
    "paole": "Áo Lễ Linh Mục: Xanh"
  },
  {
    "date": "25-08-2025",
    "title": "Lịch công giáo ngày 25-08-2025",
    "desc": "Thánh Luy, vua nước Pháp và thánh Giuse Calasanz, linh mục",
    "read": "1 Tx 1,1-5.8b-10 ; Mt 23,13-22 (X)",
    "paole": "Áo Lễ Linh Mục: Xanh"
  },
  {
    "date": "26-08-2025",
    "title": "Lịch công giáo ngày 26-08-2025",
    "desc": "Thứ Ba trong tuần thứ Hai Mươi-Nhất Mùa Quanh Năm",
    "read": "1 Tx 2,1-8 ; Mt 23,23-26 (X)",
    "paole": "Áo Lễ Linh Mục: Xanh"
  },
  {
    "date": "27-08-2025",
    "title": "Lịch công giáo ngày 27-08-2025",
    "desc": "Thánh nữ Mônica",
    "read": "1 Tx 2,9-13 ; Mt 23,27-32 (Tr)",
    "paole": "Áo Lễ Linh Mục: Trắng"
  },
  {
    "date": "28-08-2025",
    "title": "Lịch công giáo ngày 28-08-2025",
    "desc": "Thánh Augustinô, giám mục, tiến sĩ Hội Thánh",
    "read": "1 Tx 3,7-13 ; Mt 24,42-51 (Tr)",
    "paole": "Áo Lễ Linh Mục: Trắng"
  },
  {
    "date": "29-08-2025",
    "title": "Lịch công giáo ngày 29-08-2025",
    "desc": "Thánh Gioan Tẩy Giả bị trảm quyết",
    "read": "Gr 1,17-19 ; Mc 6,17-29 (Đ)",
    "paole": "Áo Lễ Linh Mục: Đỏ"
  },
  {
    "date": "30-08-2025",
    "title": "Lịch công giáo ngày 30-08-2025",
    "desc": "Thứ Bảy trong tuần thứ Hai Mươi-Nhất Mùa Quanh Năm",
    "read": "1 Tx 4,9-11 ; Mt 25,14-30 (X)",
    "paole": "Áo Lễ Linh Mục: Xanh"
  },
  {
    "date": "31-08-2025",
    "title": "Lịch công giáo ngày 31-08-2025",
    "desc": "CHÚA NHẬT XXII THƯỜNG NIÊN. Thánh vịnh tuần II",
    "read": "Hc 3,17-18.20.28-29 ; Dt 12,18-19.22-24a ; Lc 14,1.7-14 (X)",
    "paole": "Áo Lễ Linh Mục: Xanh"
  },
  {
    "date": "01-09-2025",
    "title": "Lịch công giáo ngày 01-09-2025",
    "desc": "Thứ Hai trong tuần thứ Hai Mươi-Hai Mùa Quanh Năm",
    "read": "Tx 4,13-18 ; Lc 4,16-30 (X)",
    "paole": "Áo Lễ Linh Mục: Xanh"
  },
  {
    "date": "02-09-2025",
    "title": "Lịch công giáo ngày 02-09-2025",
    "desc": "Thứ Ba trong tuần thứ Hai Mươi-Hai Mùa Quanh Năm",
    "read": "1 Tx 5,1-6.9-11 ; Lc 4,31-37 (X)",
    "paole": "Áo Lễ Linh Mục: Xanh"
  },
  {
    "date": "03-09-2025",
    "title": "Lịch công giáo ngày 03-09-2025",
    "desc": "Thánh Grêgôriô Cả, giáo hoàng, tiến sĩ Hội Thánh",
    "read": "Cl 1,1-8 ; Lc 4,38-44 (Tr)",
    "paole": "Áo Lễ Linh Mục: Trắng"
  },
  {
    "date": "04-09-2025",
    "title": "Lịch công giáo ngày 04-09-2025",
    "desc": "Thứ Năm trong tuần thứ Hai Mươi-Hai Mùa Quanh Năm",
    "read": "Cl 1,9-14 ; Lc 5,1-11 (X)",
    "paole": "Áo Lễ Linh Mục: Xanh"
  },
  {
    "date": "05-09-2025",
    "title": "Lịch công giáo ngày 05-09-2025",
    "desc": "Thánh Giuse Hoàng Lương Cảnh, trùm họ, Thánh Phêrô Nguyễn Văn Tự, linh mục, tử đạo († 1838). Thánh Têrêsa Calcutta, nữ tu",
    "read": "Mt 25, 31-46 (Đ)",
    "paole": "Áo Lễ Linh Mục: Đỏ"
  },
  {
    "date": "06-09-2025",
    "title": "Lịch công giáo ngày 06-09-2025",
    "desc": "Thứ Bảy trong tuần thứ Hai Mươi-Hai Mùa Quanh Năm",
    "read": "Cl 1,21-23 ; Lc 6,1-5 (X)",
    "paole": "Áo Lễ Linh Mục: Xanh"
  },
  {
    "date": "07-09-2025",
    "title": "Lịch công giáo ngày 07-09-2025",
    "desc": "CHÚA NHẬT XXIII THƯỜNG NIÊN. Thánh vịnh tuần III",
    "read": "Kn 9,13-18 ; Plm 9b-10.12-17 ; Lc 14,25-33 (X)",
    "paole": "Áo Lễ Linh Mục: Xanh"
  },
  {
    "date": "08-09-2025",
    "title": "Lịch công giáo ngày 08-09-2025",
    "desc": "SINH NHẬT ĐỨC TRINH NỮ MARIA",
    "read": "Mk 5,1-4a (hay Rm 8,28-30) ; Mt 1,1-16.18-23 (hay Mt 1,18-23) (Tr)",
    "paole": "Áo Lễ Linh Mục: Trắng"
  },
  {
    "date": "09-09-2025",
    "title": "Lịch công giáo ngày 09-09-2025",
    "desc": "Thánh Phêrô Claver, linh mục",
    "read": "Cl 2,6-15 ; Lc 6,12-19 (X)",
    "paole": "Áo Lễ Linh Mục: Xanh"
  },
  {
    "date": "10-09-2025",
    "title": "Lịch công giáo ngày 10-09-2025",
    "desc": "Thứ Tư trong tuần thứ Hai Mươi-Ba Mùa Quanh Năm",
    "read": "Cl 3,1-11 ; Lc 6,20-26 (X)",
    "paole": "Áo Lễ Linh Mục: Xanh"
  },
  {
    "date": "11-09-2025",
    "title": "Lịch công giáo ngày 11-09-2025",
    "desc": "Thứ Năm trong tuần thứ Hai Mươi-Ba Mùa Quanh Năm",
    "read": "Cl 3,12-17 ; Lc 6,27-38 (X)",
    "paole": "Áo Lễ Linh Mục: Xanh"
  },
  {
    "date": "12-09-2025",
    "title": "Lịch công giáo ngày 12-09-2025",
    "desc": "Danh Thánh Đức Maria",
    "read": "1 Tm 1,1-2.12-14 ; Lc 6,39-42. Lễ Đức Mẹ (Tr): GI 4,4-7 (hay Ep 1,3-6.11-12) ; Lc 1,39-47 (X)",
    "paole": "Áo Lễ Linh Mục: Xanh"
  },
  {
    "date": "13-09-2025",
    "title": "Lịch công giáo ngày 13-09-2025",
    "desc": "Thánh Gioan Kim Khẩu, giám mục, tiến sĩ Hội Thánh",
    "read": "1 Tm 1,15-17 ; Lc 6,43-49 (Tr)",
    "paole": "Áo Lễ Linh Mục: Trắng"
  },
  {
    "date": "14-09-2025",
    "title": "Lịch công giáo ngày 14-09-2025",
    "desc": "CHÚA NHẬT XXIV THƯỜNG NIÊN. SUY TÔN THÁNH GIÁ",
    "read": "Ds 21,4b-9 ; Pl 2,6-11 ; Ga 3,13-17 (Đ)",
    "paole": "Áo Lễ Linh Mục: Đỏ"
  },
  {
    "date": "15-09-2025",
    "title": "Lịch công giáo ngày 15-09-2025",
    "desc": "Thánh vịnh tuần IV. Đức Mẹ Sầu Bi",
    "read": "Dt 5,7-9 ; Ga 19,25-27 (hay Lc 2,33-35) (Tr)",
    "paole": "Áo Lễ Linh Mục: Trắng"
  },
  {
    "date": "16-09-2025",
    "title": "Lịch công giáo ngày 16-09-2025",
    "desc": "Thánh Cornêliô, giáo hoàng, tử đạo và thánh Cyprianô, giám mục, tử đạo",
    "read": "1 Tm 3,1-13 ; Lc 7,11-17 (Đ)",
    "paole": "Áo Lễ Linh Mục: Đỏ"
  },
  {
    "date": "17-09-2025",
    "title": "Lịch công giáo ngày 17-09-2025",
    "desc": "Thánh Robertô Bellarminô, giám mục, tiến sĩ Hội Thánh. Thánh Hildegardis Bingensis, trinh nữ, tiến sĩ Hội Thánh. Thánh Emmanuel Nguyễn Văn Triệu, linh mục, tử đạo († 1798)",
    "read": "1 Tm 3,14-16 ; Lc 7,31-35 (X)",
    "paole": "Áo Lễ Linh Mục: Xanh"
  },
  {
    "date": "18-09-2025",
    "title": "Lịch công giáo ngày 18-09-2025",
    "desc": "Thánh Đaminh Vũ Đức Trạch (Đoài), linh mục, tử đạo († 1840)",
    "read": "1 Tm 4,12-16 ; Lc 7,36-50 (X)",
    "paole": "Áo Lễ Linh Mục: Xanh"
  },
  {
    "date": "19-09-2025",
    "title": "Lịch công giáo ngày 19-09-2025",
    "desc": "Thánh Januariô, giám mục, tử đạo.",
    "read": "1 Tm 6,2c-12 ; Lc 8,1-3 (Đ)",
    "paole": "Áo Lễ Linh Mục: Đỏ"
  },
  {
    "date": "20-09-2025",
    "title": "Lịch công giáo ngày 20-09-2025",
    "desc": "Thánh Anrê Kim Têgon, thánh Phaolô Chong Hasang và các bạn, tử đạo. Thánh Jean Charles Cornay Tân, linh mục, tử đạo († 1837)",
    "read": "1 Tm 6,13-16 ; Lc 8,4-15 (Đ)",
    "paole": "Áo Lễ Linh Mục: Đỏ"
  },
  {
    "date": "21-09-2025",
    "title": "Lịch công giáo ngày 21-09-2025",
    "desc": "CHÚA NHẬT XXV THƯỜNG NIÊN. Thánh vịnh tuần I",
    "read": "Am 8,4-7 ; 1 Tm 2,1-8 ; Lc 16,1-13 (hay Lc 16,10-13) (X)",
    "paole": "Áo Lễ Linh Mục: Xanh"
  },
  {
    "date": "22-09-2025",
    "title": "Lịch công giáo ngày 22-09-2025",
    "desc": "Thứ Hai trong tuần thứ Hai Mươi-Năm Mùa Quanh Năm",
    "read": "Er 1,1-6 ; Lc 8,16-18 (X)",
    "paole": "Áo Lễ Linh Mục: Trắng"
  },
  {
    "date": "23-09-2025",
    "title": "Lịch công giáo ngày 23-09-2025",
    "desc": "Thánh Piô Pietrelcina, linh mục",
    "read": "Er 6,7-8,12b.14-20 ; Lc 8,19-21 (Tr)",
    "paole": "Áo Lễ Linh Mục: Trắng"
  },
  {
    "date": "24-09-2025",
    "title": "Lịch công giáo ngày 24-09-2025",
    "desc": "Thứ Tư trong tuần thứ Hai Mươi-Năm Mùa Quanh Năm",
    "read": "Er 9,5-9 ; Lc 9,1-6 (X)",
    "paole": "Áo Lễ Linh Mục: Xanh"
  },
  {
    "date": "25-09-2025",
    "title": "Lịch công giáo ngày 25-09-2025",
    "desc": "Thứ Năm trong tuần thứ Hai Mươi-Năm Mùa Quanh Năm",
    "read": "Kg 1,1-8 ; Lc 9,7-9 (X)",
    "paole": "Áo Lễ Linh Mục: Xanh"
  },
  {
    "date": "26-09-2025",
    "title": "Lịch công giáo ngày 26-09-2025",
    "desc": "Thánh Cosma và thánh Đamianô, tử đạo",
    "read": "Kg 1,15b–2,9 ; Lc 9,18-22 (X)",
    "paole": "Áo Lễ Linh Mục: Xanh"
  },
  {
    "date": "27-09-2025",
    "title": "Lịch công giáo ngày 27-09-2025",
    "desc": "Thánh Vinh Sơn Phaolô, linh mục",
    "read": "Dcr 2,5-9.14-15a ; Lc 9,43b-45 (Tr)",
    "paole": "Áo Lễ Linh Mục: Trắng"
  },
  {
    "date": "28-09-2025",
    "title": "Lịch công giáo ngày 28-09-2025",
    "desc": "CHÚA NHẬT XXVI THƯỜNG NIÊN. Thánh vịnh tuần II",
    "read": "Am 6,1a.4-7 ; 1 Tm 6,11-16 ; Lc 16,19-31 (X)",
    "paole": "Áo Lễ Linh Mục: Xanh"
  },
  {
    "date": "29-09-2025",
    "title": "Lịch công giáo ngày 29-09-2025",
    "desc": "CÁC TỔNG LÃNH THIÊN THẦN MICHAEL, GABRIEL, RAPHAEL",
    "read": "Ðn 7,9-10.13-14 (hay Kh 12,7-12a ; Ga 1,47-51 (Tr)",
    "paole": "Áo Lễ Linh Mục: Trắng"
  },
  {
    "date": "30-09-2025",
    "title": "Lịch công giáo ngày 30-09-2025",
    "desc": "Thánh Giêrônimô, linh mục, tiến sĩ Hội Thánh",
    "read": "Dcr 8,20-23 ; Lc 9,51-56 (Tr)",
    "paole": "Áo Lễ Linh Mục: Trắng"
  },
  {
    "date": "01-10-2025",
    "title": "Lịch công giáo ngày 01-10-2025",
    "desc": "Thánh Tê-rê-xa Hài Đồng Giê-su, trinh nữ, tiến sĩ Hội Thánh",
    "read": "Nkm 2:1-8; Tv 137:1-2,3,4-5,6; Lc 9:57-62",
    "paole": "Áo Lễ Linh Mục: Trắng"
  },
  {
    "date": "02-10-2025",
    "title": "Lịch công giáo ngày 02-10-2025",
    "desc": "Các thiên thần hộ thủ",
    "read": "Nkm 8:1-4,5-6,7-12; Tv 19:8,9,10,11; Lc 10:1-12",
    "paole": "Áo Lễ Linh Mục: Trắng"
  },
  {
    "date": "03-10-2025",
    "title": "Lịch công giáo ngày 03-10-2025",
    "desc": "Thứ Sáu trong tuần thứ Hai Mươi-Sáu Mùa Quanh Năm",
    "read": "Br 1:15-22; Tv 79:1-2,3-5,8,9; Lc 10:13-16",
    "paole": "Áo Lễ Linh Mục: Xanh"
  },
  {
    "date": "04-10-2025",
    "title": "Lịch công giáo ngày 04-10-2025",
    "desc": "Thánh Phan-xi-cô thành Át-xi-di",
    "read": "Br 4:5-12,27-29; Tv 69:33-35,36-37; Lc 10:17-24",
    "paole": "Áo Lễ Linh Mục: Trắng"
  },
  {
    "date": "05-10-2025",
    "title": "Lịch công giáo ngày 05-10-2025",
    "desc": "Đức Mẹ Mân Côi",
    "read": "Kb 1:2-3,2; Tv 95:1-2,6-7,8-9; 2 Tm 1:6-8,13-14; Lc 17:5-10",
    "paole": "Áo Lễ Linh Mục: Trắng"
  },
  {
    "date": "06-10-2025",
    "title": "Lịch công giáo ngày 06-10-2025",
    "desc": "Thứ Hai trong tuần thứ Hai Mươi-Bảy Mùa Quanh Năm",
    "read": "St 1:1; St 2:1,112; Lc 10:25-37",
    "paole": "Áo Lễ Linh Mục: Xanh"
  },
  {
    "date": "07-10-2025",
    "title": "Lịch công giáo ngày 07-10-2025",
    "desc": "Thứ Ba trong tuần thứ Hai Mươi-Bảy Mùa Quanh Năm",
    "read": "St 3:1-10; Tv 130:1-2,3-4,7-8; Lc 10:38-42",
    "paole": "Áo Lễ Linh Mục: Xanh"
  },
  {
    "date": "08-10-2025",
    "title": "Lịch công giáo ngày 08-10-2025",
    "desc": "Thứ Tư trong tuần thứ Hai Mươi-Bảy Mùa Quanh Năm",
    "read": "St 4:1-11; Tv 86:3-4,5-6,9-10; Lc 11:1-4",
    "paole": "Áo Lễ Linh Mục: Xanh"
  },
  {
    "date": "09-10-2025",
    "title": "Lịch công giáo ngày 09-10-2025",
    "desc": "Thứ Năm trong tuần thứ Hai Mươi-Bảy Mùa Quanh Năm",
    "read": "St 3:13-20; Tv 1:1,1-2,3,4,6; Lc 11:5-13",
    "paole": "Áo Lễ Linh Mục: Xanh"
  },
  {
    "date": "10-10-2025",
    "title": "Lịch công giáo ngày 10-10-2025",
    "desc": "Thứ Sáu trong tuần thứ Hai Mươi-Bảy Mùa Quanh Năm",
    "read": "Ge 1:13-15; Tv 9:2-3,6,16,8-9; Lc 11:15-26",
    "paole": "Áo Lễ Linh Mục: Xanh"
  },
  {
    "date": "11-10-2025",
    "title": "Lịch công giáo ngày 11-10-2025",
    "desc": "Thứ Bảy trong tuần thứ Hai Mươi-Bảy Mùa Quanh Năm",
    "read": "Ge 4:12-21; Tv 97:1-2,5-6,11-12; Lc 11:27-28",
    "paole": "Áo Lễ Linh Mục: Xanh"
  },
  {
    "date": "12-10-2025",
    "title": "Lịch công giáo ngày 12-10-2025",
    "desc": "Chúa Nhật thứ Hai Mươi-Tám Mùa Quanh Năm",
    "read": "2 V 5:14-17; Tv 98:1,2-3,3-4; 2 Tm 2:8-13; Lc 17:11-19",
    "paole": "Áo Lễ Linh Mục: Xanh"
  },
  {
    "date": "13-10-2025",
    "title": "Lịch công giáo ngày 13-10-2025",
    "desc": "Thứ Hai trong tuần thứ Hai Mươi-Tám Mùa Quanh Năm",
    "read": "Rm 1:1-7; Tv 98:1,2-3,3-4; Lc 11:29-32",
    "paole": "Áo Lễ Linh Mục: Xanh"
  },
  {
    "date": "14-10-2025",
    "title": "Lịch công giáo ngày 14-10-2025",
    "desc": "Thứ Ba trong tuần thứ Hai Mươi-Tám Mùa Quanh Năm",
    "read": "Rm 1:16-25; Tv 19:2-3,4-5; Lc 11:37-41",
    "paole": "Áo Lễ Linh Mục: Xanh"
  },
  {
    "date": "15-10-2025",
    "title": "Lịch công giáo ngày 15-10-2025",
    "desc": "Thánh Tê-rê-xa Giê-su, trinh nữ, tiến sĩ Hội Thánh",
    "read": "Rm 2:1-11; Tv 62:2-3,6-7,9; Lc 11:42-46",
    "paole": "Áo Lễ Linh Mục: Trắng"
  },
  {
    "date": "16-10-2025",
    "title": "Lịch công giáo ngày 16-10-2025",
    "desc": "Thứ Năm trong tuần thứ Hai Mươi-Tám Mùa Quanh Năm",
    "read": "Rm 3:21-29; Tv 130:1-2,3-4,5-6; Lc 11:47-54",
    "paole": "Áo Lễ Linh Mục: Xanh"
  },
  {
    "date": "17-10-2025",
    "title": "Lịch công giáo ngày 17-10-2025",
    "desc": "Thánh I-nha-xi-ô thành An-ti-ô-khi-a, giám mục, tử đạo",
    "read": "Rm 4:1-8; Tv 32:1-2,5,11; Lc 12:1-7",
    "paole": "Áo Lễ Linh Mục: Đỏ"
  },
  {
    "date": "18-10-2025",
    "title": "Lịch công giáo ngày 18-10-2025",
    "desc": "Thánh Lu-ca, tác giả sách Tin Mừng",
    "read": "Rm 4:13,16-18; Tv 105:6-7,8-9,42-43; Lc 12:8-12",
    "paole": "Áo Lễ Linh Mục: Đỏ"
  },
  {
    "date": "19-10-2025",
    "title": "Lịch công giáo ngày 19-10-2025",
    "desc": "Chúa Nhật thứ Hai Mươi-Chín Mùa Quanh Năm",
    "read": "Xh 17:8-13; Tv 121:1-2,3-4,5-6,7-8; 2 Tm 3:144; Lc 18:1-8",
    "paole": "Áo Lễ Linh Mục: Xanh"
  },
  {
    "date": "20-10-2025",
    "title": "Lịch công giáo ngày 20-10-2025",
    "desc": "Thứ Hai trong tuần thứ Hai Mươi-Chín Mùa Quanh Năm",
    "read": "Rm 4:20-25; Lc 1:69-70,71-72,73,75; Lc 12:13-21",
    "paole": "Áo Lễ Linh Mục: Xanh"
  },
  {
    "date": "21-10-2025",
    "title": "Lịch công giáo ngày 21-10-2025",
    "desc": "Thứ Ba trong tuần thứ Hai Mươi-Chín Mùa Quanh Năm",
    "read": "Rm 5:12,15,17-19,20-21; Tv 40:7-8,89,10,17; Lc 12:35-38",
    "paole": "Áo Lễ Linh Mục: Xanh"
  },
  {
    "date": "22-10-2025",
    "title": "Lịch công giáo ngày 22-10-2025",
    "desc": "Thứ Tư trong tuần thứ Hai Mươi-Chín Mùa Quanh Năm",
    "read": "Rm 6:12-18; Tv 124:1-3,4-6,7-8; Lc 12:39-48",
    "paole": "Áo Lễ Linh Mục: Xanh"
  },
  {
    "date": "23-10-2025",
    "title": "Lịch công giáo ngày 23-10-2025",
    "desc": "Thứ Năm trong tuần thứ Hai Mươi-Chín Mùa Quanh Năm",
    "read": "Rm 6:19-23; Tv 1:1-2,3,4,6; Lc 12:49-53",
    "paole": "Áo Lễ Linh Mục: Xanh"
  },
  {
    "date": "24-10-2025",
    "title": "Lịch công giáo ngày 24-10-2025",
    "desc": "Thứ Sáu trong tuần thứ Hai Mươi-Chín Mùa Quanh Năm",
    "read": "Rm 7:18-25; Tv 119:66,68,76,77,93,94; Lc 12:54-59",
    "paole": "Áo Lễ Linh Mục: Xanh"
  },
  {
    "date": "25-10-2025",
    "title": "Lịch công giáo ngày 25-10-2025",
    "desc": "Thứ Bảy trong tuần thứ Hai Mươi-Chín Mùa Quanh Năm",
    "read": "Rm 8:1-11; Tv 24:1-2,3-4,5-6; Lc 13:1-9",
    "paole": "Áo Lễ Linh Mục: Xanh"
  },
  {
    "date": "26-10-2025",
    "title": "Lịch công giáo ngày 26-10-2025",
    "desc": "Chúa Nhật thứ Ba Mươi Mùa Quanh Năm",
    "read": "Hc 35:12-14,16-18; Tv 34:2-3,17-18,19-23; 2 Tm 4:6-8,16-18; Lc 18:9-14",
    "paole": "Áo Lễ Linh Mục: Xanh"
  },
  {
    "date": "27-10-2025",
    "title": "Lịch công giáo ngày 27-10-2025",
    "desc": "Thứ Hai trong tuần thứ Ba Mươi Mùa Quanh Năm",
    "read": "Rm 8:12-17; Tv 68:2,4,6-7,20-21; Lc 13:10-17",
    "paole": "Áo Lễ Linh Mục: Xanh"
  },
  {
    "date": "28-10-2025",
    "title": "Lịch công giáo ngày 28-10-2025",
    "desc": "Thánh Si-mon và thánh Giu-đa, tông đồ",
    "read": "Rm 8:18-25; Tv 126:1-2,2-3,4-5,6; Lc 13:18-21",
    "paole": "Áo Lễ Linh Mục: Đỏ"
  },
  {
    "date": "29-10-2025",
    "title": "Lịch công giáo ngày 29-10-2025",
    "desc": "Thứ Tư trong tuần thứ Ba Mươi Mùa Quanh Năm",
    "read": "Rm 8:26-30; Tv 13:4-5,6; Lc 13:22-30",
    "paole": "Áo Lễ Linh Mục: Xanh"
  },
  {
    "date": "30-10-2025",
    "title": "Lịch công giáo ngày 30-10-2025",
    "desc": "Thứ Năm trong tuần thứ Ba Mươi Mùa Quanh Năm",
    "read": "Rm 8:31-39; Tv 109:21-22,26-27,30-31; Lc 13:31-35",
    "paole": "Áo Lễ Linh Mục: Xanh"
  },
  {
    "date": "31-10-2025",
    "title": "Lịch công giáo ngày 31-10-2025",
    "desc": "Thứ Sáu trong tuần thứ Ba Mươi Mùa Quanh Năm",
    "read": "Rm 9:1-5; Tv 147:12-13,14-15,19-20; Lc 14:1-6",
    "paole": "Áo Lễ Linh Mục: Xanh"
  },
  {
    "date": "01-11-2025",
    "title": "Lịch công giáo ngày 01-11-2025",
    "desc": "Các Thánh Nam Nữ",
    "read": "Rm 11:1-2,11-12,25-29; Tv 94:12-13,14-15,17-18; Lc 14:1,7-11",
    "paole": "Áo Lễ Linh Mục: Trắng"
  },
  {
    "date": "02-11-2025",
    "title": "Lịch công giáo ngày 02-11-2025",
    "desc": "Cầu Cho Các Tín Hữu Đã Qua Đời",
    "read": "Rm 6:3-9; Ga 6:51-59; Kh 3:1-9; Lc 23:33,39-43; Rm 5:4-11; Ga 17:24-26",
    "paole": "Áo Lễ Linh Mục: Tím"
  },
  {
    "date": "03-11-2025",
    "title": "Lịch công giáo ngày 03-11-2025",
    "desc": "Thứ Hai trong tuần thứ Ba Mươi-Nhất Mùa Quanh Năm",
    "read": "Rm 11:29-36; Tv 69:30-31,33-34,36-37; Lc 14:12-14",
    "paole": "Áo Lễ Linh Mục: Xanh"
  },
  {
    "date": "04-11-2025",
    "title": "Lịch công giáo ngày 04-11-2025",
    "desc": "Thánh Ca-rô-lô Bô-rô-mê-ô, giám mục",
    "read": "Rm 12:5-16; Tv 14:15-24",
    "paole": "Áo Lễ Linh Mục: Trắng"
  },
  {
    "date": "05-11-2025",
    "title": "Lịch công giáo ngày 05-11-2025",
    "desc": "Thứ Tư trong tuần thứ Ba Mươi-Nhất Mùa Quanh Năm",
    "read": "Rm 13:8-10; Tv 112:1-2,4-5,9; Lc 14:25-33",
    "paole": "Áo Lễ Linh Mục: Xanh"
  },
  {
    "date": "06-11-2025",
    "title": "Lịch công giáo ngày 06-11-2025",
    "desc": "Thứ Năm trong tuần thứ Ba Mươi-Nhất Mùa Quanh Năm",
    "read": "Rm 14:7-12; Tv 27:1,4,13-14; Lc 15:1-10",
    "paole": "Áo Lễ Linh Mục: Xanh"
  },
  {
    "date": "07-11-2025",
    "title": "Lịch công giáo ngày 07-11-2025",
    "desc": "Thứ Sáu trong tuần thứ Ba Mươi-Nhất Mùa Quanh Năm",
    "read": "Rm 15:14-21; Tv 98:1,2-3,3-4; Lc 16:1-8",
    "paole": "Áo Lễ Linh Mục: Xanh"
  },
  {
    "date": "08-11-2025",
    "title": "Lịch công giáo ngày 08-11-2025",
    "desc": "Thứ Bảy trong tuần thứ Ba Mươi-Nhất Mùa Quanh Năm",
    "read": "Rm 16:3-9,16,22-27; Tv 145:2-3,4-5,10-11; Lc 16:9-15",
    "paole": "Áo Lễ Linh Mục: Xanh"
  },
  {
    "date": "09-11-2025",
    "title": "Lịch công giáo ngày 09-11-2025",
    "desc": "Cung hiến thánh đường La-tê-ra-nô",
    "read": "2 Mcb 7:1-2,9-14; Tv 17:1,5-6,8-1522; Lc 20:27-38; Lc 20:27,34-38",
    "paole": "Áo Lễ Linh Mục: Trắng"
  },
  {
    "date": "10-11-2025",
    "title": "Lịch công giáo ngày 10-11-2025",
    "desc": "Thánh Lê-ô Cả, giáo hoàng, tiến sĩ Hội Thánh",
    "read": "Kn 1:1-7; Tv 139:1-3,4-6,7-8,9-10; Lc 17:1-6",
    "paole": "Áo Lễ Linh Mục: Trắng"
  },
  {
    "date": "11-11-2025",
    "title": "Lịch công giáo ngày 11-11-2025",
    "desc": "Thánh Mác-ti-nô thành Tua, giám mục",
    "read": "Kn 2:23-3; Tv 34:2-3,16-17,18-19; Lc 17:7-10",
    "paole": "Áo Lễ Linh Mục: Trắng"
  },
  {
    "date": "12-11-2025",
    "title": "Lịch công giáo ngày 12-11-2025",
    "desc": "Thánh Giô-sa-phát, giám mục, tử đạo",
    "read": "Kn 6:2-11; Tv 82:3-4,6-7; Lc 17:11-19",
    "paole": "Áo Lễ Linh Mục: Đỏ"
  },
  {
    "date": "13-11-2025",
    "title": "Lịch công giáo ngày 13-11-2025",
    "desc": "Thánh Frances Xavier Cabrini, Đt",
    "read": "Kn 7:22; Kn 8:1; Tv 119:89,90,91,130,135,175; Lc 17:20-25",
    "paole": "Áo Lễ Linh Mục: Xanh"
  },
  {
    "date": "14-11-2025",
    "title": "Lịch công giáo ngày 14-11-2025",
    "desc": "Thứ Sáu trong tuần thứ Ba Mươi-Hai Mùa Quanh Năm",
    "read": "Kn 13:1-9; Tv 19:2-3,4-5; Lc 17:26-37",
    "paole": "Áo Lễ Linh Mục: Xanh"
  },
  {
    "date": "15-11-2025",
    "title": "Lịch công giáo ngày 15-11-2025",
    "desc": "Thứ Bảy trong tuần thứ Ba Mươi-Hai Mùa Quanh Năm",
    "read": "Kn 18:14-16; Tv 105:2-3,36-37,42-43; Lc 18:1-8",
    "paole": "Áo Lễ Linh Mục: Xanh"
  },
  {
    "date": "16-11-2025",
    "title": "Lịch công giáo ngày 16-11-2025",
    "desc": "Thánh An-rê Trần An Dũng Lạc và các bạn, tử đạo",
    "read": "St 3:19-20; Tv 98:5-6,7-8,923; Lc 21:5-19",
    "paole": "Áo Lễ Linh Mục: Đỏ"
  },
  {
    "date": "17-11-2025",
    "title": "Lịch công giáo ngày 17-11-2025",
    "desc": "Thánh nữ Ê-li-sa-bet nước Hung-ga-ri",
    "read": "1 Mcb 1:10-15,41-43,54-57,62-63; Tv 119:53,61,134,150,155,158; Lc 18:35-43",
    "paole": "Áo Lễ Linh Mục: Trắng"
  },
  {
    "date": "18-11-2025",
    "title": "Lịch công giáo ngày 18-11-2025",
    "desc": "Thứ Ba trong tuần thứ Ba Mươi-Ba Mùa Quanh Năm",
    "read": "2 Mcb 6:18-31; Tv 3:2-3,4-5,6-8; Lc 19:1-10",
    "paole": "Áo Lễ Linh Mục: Xanh"
  },
  {
    "date": "19-11-2025",
    "title": "Lịch công giáo ngày 19-11-2025",
    "desc": "Thứ Tư trong tuần thứ Ba Mươi-Ba Mùa Quanh Năm",
    "read": "2 Mcb 7:1,20-31; Tv 17:1,5-6,8,15; Lc 19:11-28",
    "paole": "Áo Lễ Linh Mục: Xanh"
  },
  {
    "date": "20-11-2025",
    "title": "Lịch công giáo ngày 20-11-2025",
    "desc": "Thứ Năm trong tuần thứ Ba Mươi-Ba Mùa Quanh Năm",
    "read": "1 Mcb 2:15-29; Tv 50:1-2,5-6,14-15; Lc 19:41-44",
    "paole": "Áo Lễ Linh Mục: Xanh"
  },
  {
    "date": "21-11-2025",
    "title": "Lịch công giáo ngày 21-11-2025",
    "desc": "Đức Mẹ dâng mình trong đền thờ",
    "read": "1 Mcb 4:36-37,52-59; 1 Sb 29:10,11,11-12,12; Lc 19:45-48",
    "paole": "Áo Lễ Linh Mục: Trắng"
  },
  {
    "date": "22-11-2025",
    "title": "Lịch công giáo ngày 22-11-2025",
    "desc": "Thánh Xê-xi-li-a, trinh nữ, tử đạo",
    "read": "1 Mcb 6:1-13; Tv 9:2-3,4,6,16,19; Lc 20:27-40",
    "paole": "Áo Lễ Linh Mục: Đỏ"
  },
  {
    "date": "23-11-2025",
    "title": "Lịch công giáo ngày 23-11-2025",
    "desc": "Lễ Chúa Kitô Vua",
    "read": "2 Sm 5:1-3; Tv 122:1-2,3-4,4-5; Cl 1:12-20; Lc 23:35-43",
    "paole": "Áo Lễ Linh Mục: Trắng"
  },
  {
    "date": "24-11-2025",
    "title": "Lịch công giáo ngày 24-11-2025",
    "desc": "Thứ Hai trong tuần thứ Ba Mươi-Tư Mùa Quanh Năm",
    "read": "St 1:1-6,8-203; Lc 21:1-4",
    "paole": "Áo Lễ Linh Mục: Đỏ"
  },
  {
    "date": "25-11-2025",
    "title": "Lịch công giáo ngày 25-11-2025",
    "desc": "Thứ Ba trong tuần thứ Ba Mươi-Tư Mùa Quanh Năm",
    "read": "St 2:31-453; Lc 21:5-11",
    "paole": "Áo Lễ Linh Mục: Xanh"
  },
  {
    "date": "26-11-2025",
    "title": "Lịch công giáo ngày 26-11-2025",
    "desc": "Thứ Tư trong tuần thứ Ba Mươi-Tư Mùa Quanh Năm",
    "read": "St 5:1-6,13-14,16-17,23-283; Lc 21:12-19",
    "paole": "Áo Lễ Linh Mục: Xanh"
  },
  {
    "date": "27-11-2025",
    "title": "Lịch công giáo ngày 27-11-2025",
    "desc": "Thứ Năm trong tuần thứ Ba Mươi-Tư Mùa Quanh Năm",
    "read": "St 6:12-283; Lc 21:20-28",
    "paole": "Áo Lễ Linh Mục: Xanh"
  },
  {
    "date": "28-11-2025",
    "title": "Lịch công giáo ngày 28-11-2025",
    "desc": "Thứ Sáu trong tuần thứ Ba Mươi-Tư Mùa Quanh Năm",
    "read": "St 7:2-143; Lc 21:29-33",
    "paole": "Áo Lễ Linh Mục: Xanh"
  },
  {
    "date": "29-11-2025",
    "title": "Lịch công giáo ngày 29-11-2025",
    "desc": "Thứ Bảy trong tuần thứ Ba Mươi-Tư Mùa Quanh Năm",
    "read": "St 7:15-273; Lc 21:34-36",
    "paole": "Áo Lễ Linh Mục: Xanh"
  },
  {
    "date": "30-11-2025",
    "title": "Lịch công giáo ngày 30-11-2025",
    "desc": "Chúa Nhật thứ Nhất Mùa Vọng",
    "read": "Gr 33:14-16; Tv 25:4-5,8-9,10-1413; Lc 21:25-28,34-36",
    "paole": "Áo Lễ Linh Mục: Tím"
  },
  {
    "date": "01-12-2025",
    "title": "Lịch công giáo ngày 01-12-2025",
    "desc": "Thứ Hai trong tuần thứ Nhất Mùa Vọng",
    "read": "Is 2:1-5; Is 4:2-6; Tv 122:1-2,3-4,4-5,6-7,8-9; Mt 8:5-11",
    "paole": "Áo Lễ Linh Mục: Tím"
  },
  {
    "date": "02-12-2025",
    "title": "Lịch công giáo ngày 02-12-2025",
    "desc": "Thứ Ba trong tuần thứ Nhất Mùa Vọng",
    "read": "Is 11:1-10; Tv 72:1,7-8,12-13,17; Lc 10:21-24",
    "paole": "Áo Lễ Linh Mục: Tím"
  },
  {
    "date": "03-12-2025",
    "title": "Lịch công giáo ngày 03-12-2025",
    "desc": "Thánh Phan-xi-cô Xa-vi-e, linh mục",
    "read": "Is 25:6-10; Tv 23:1-3,3-4,5,6; Mt 15:29-37",
    "paole": "Áo Lễ Linh Mục: Trắng"
  },
  {
    "date": "04-12-2025",
    "title": "Lịch công giáo ngày 04-12-2025",
    "desc": "Thứ Năm trong tuần thứ Nhất Mùa Vọng",
    "read": "Is 26:1-6; Tv 118:1,8-9,19-21,25-27; Mt 7:21,24-27",
    "paole": "Áo Lễ Linh Mục: Tím"
  },
  {
    "date": "05-12-2025",
    "title": "Lịch công giáo ngày 05-12-2025",
    "desc": "Thứ Sáu trong tuần thứ Nhất Mùa Vọng",
    "read": "Is 29:17-24; Tv 27:1,4,13-14; Mt 9:27-31",
    "paole": "Áo Lễ Linh Mục: Tím"
  },
  {
    "date": "06-12-2025",
    "title": "Lịch công giáo ngày 06-12-2025",
    "desc": "Thứ Bảy trong tuần thứ Nhất Mùa Vọng",
    "read": "Is 30:19-21,23-26; Tv 147:1-2,3-4,5-6; Mt 9:35; Mt 10:1,6-8",
    "paole": "Áo Lễ Linh Mục: Tím"
  },
  {
    "date": "07-12-2025",
    "title": "Lịch công giáo ngày 07-12-2025",
    "desc": "Chúa Nhật thứ Hai Mùa Vọng",
    "read": "Br 5:1-9; Tv 126:1-2,2-3,4-5,6; Pl 1:4-6,8-11; Lc 3:1-6",
    "paole": "Áo Lễ Linh Mục: Tím"
  },
  {
    "date": "08-12-2025",
    "title": "Lịch công giáo ngày 08-12-2025",
    "desc": "Đức Maria vô nhiễm nguyên tội",
    "read": "Is 35:1-10; Tv 85:9-10,11-12,13-14; Lc 5:17-26",
    "paole": "Áo Lễ Linh Mục: Trắng"
  },
  {
    "date": "09-12-2025",
    "title": "Lịch công giáo ngày 09-12-2025",
    "desc": "Thứ Ba trong tuần thứ Hai Mùa Vọng",
    "read": "Is 40:1-11; Tv 96:1-2,3,10,11-12,13; Mt 18:12-14",
    "paole": "Áo Lễ Linh Mục: Tím"
  },
  {
    "date": "10-12-2025",
    "title": "Lịch công giáo ngày 10-12-2025",
    "desc": "Thứ Tư trong tuần thứ Hai Mùa Vọng",
    "read": "Is 40:25-31; Tv 103:1-2,3-4,8,10; Mt 11:28-30",
    "paole": "Áo Lễ Linh Mục: Tím"
  },
  {
    "date": "11-12-2025",
    "title": "Lịch công giáo ngày 11-12-2025",
    "desc": "Thứ Năm trong tuần thứ Hai Mùa Vọng",
    "read": "Is 41:13-20; Tv 145:1,9,10-11,12-13; Mt 11:11-15",
    "paole": "Áo Lễ Linh Mục: Tím"
  },
  {
    "date": "12-12-2025",
    "title": "Lịch công giáo ngày 12-12-2025",
    "desc": "Thứ Sáu trong tuần thứ Hai Mùa Vọng",
    "read": "Is 48:17-19; Tv 1:1-2,3,4,6; Mt 11:16-19",
    "paole": "Áo Lễ Linh Mục: Tím"
  },
  {
    "date": "13-12-2025",
    "title": "Lịch công giáo ngày 13-12-2025",
    "desc": "Thánh Lu-xi-a, trinh nữ, tử đạo",
    "read": "Hc 48:1-4,9-11; Tv 80:2-3,15-16,18-19; Mt 17:10-13",
    "paole": "Áo Lễ Linh Mục: Đỏ"
  },
  {
    "date": "14-12-2025",
    "title": "Lịch công giáo ngày 14-12-2025",
    "desc": "Chúa Nhật thứ Ba Mùa Vọng",
    "read": "Xp 3:14-18; Is 12:2-3,4,5-6; Pl 4:4-7; Lc 3:10-18",
    "paole": "Áo Lễ Linh Mục: Tím"
  },
  {
    "date": "15-12-2025",
    "title": "Lịch công giáo ngày 15-12-2025",
    "desc": "Thứ Hai trong tuần thứ Ba Mùa Vọng",
    "read": "Ds 24:2-7,15-17; Tv 25:4-5,6-7,8-9; Mt 21:23-27",
    "paole": "Áo Lễ Linh Mục: Tím"
  },
  {
    "date": "16-12-2025",
    "title": "Lịch công giáo ngày 16-12-2025",
    "desc": "Thứ Ba trong tuần thứ Ba Mùa Vọng",
    "read": "Xp 3:1-2,9-13; Tv 34:2-3,6-8,17-18,19,23; Mt 21:28-32",
    "paole": "Áo Lễ Linh Mục: Tím"
  },
  {
    "date": "17-12-2025",
    "title": "Lịch công giáo ngày 17-12-2025",
    "desc": "Thứ Tư trong tuần thứ Ba Mùa Vọng",
    "read": "St 49:2,8-10; Tv 72:3-4,7-8,17; Mt 1:1-17",
    "paole": "Áo Lễ Linh Mục: Tím"
  },
  {
    "date": "18-12-2025",
    "title": "Lịch công giáo ngày 18-12-2025",
    "desc": "Thứ Năm trong tuần thứ Ba Mùa Vọng",
    "read": "Gr 23:5-8; Tv 72:1,12-13,18-19; Mt 1:18-24",
    "paole": "Áo Lễ Linh Mục: Tím"
  },
  {
    "date": "19-12-2025",
    "title": "Lịch công giáo ngày 19-12-2025",
    "desc": "Thứ Sáu trong tuần thứ Ba Mùa Vọng",
    "read": "Tl 13:2-7,24-25; Tv 71:3-4,5-6,16-17; Lc 1:5-25",
    "paole": "Áo Lễ Linh Mục: Tím"
  },
  {
    "date": "20-12-2025",
    "title": "Lịch công giáo ngày 20-12-2025",
    "desc": "Thứ Bảy trong tuần thứ Ba Mùa Vọng",
    "read": "Is 7:10-14; Tv 24:1-2,3-4,5-6; Lc 1:26-38",
    "paole": "Áo Lễ Linh Mục: Tím"
  },
  {
    "date": "21-12-2025",
    "title": "Lịch công giáo ngày 21-12-2025",
    "desc": "Chúa Nhật thứ Tư Mùa Vọng",
    "read": "St 5:1-4; Tv 80:2-3,15-16,18-19; Dt 10:5-10; Lc 1:39-45",
    "paole": "Áo Lễ Linh Mục: Tím"
  },
  {
    "date": "22-12-2025",
    "title": "Lịch công giáo ngày 22-12-2025",
    "desc": "Thứ Hai trong tuần thứ Tư Mùa Vọng",
    "read": "1 Sm 1:24-28; 1 Sm 2:1,4-5,6-7,8; Lc 1:46-56",
    "paole": "Áo Lễ Linh Mục: Tím"
  },
  {
    "date": "23-12-2025",
    "title": "Lịch công giáo ngày 23-12-2025",
    "desc": "Thứ Ba trong tuần thứ Tư Mùa Vọng",
    "read": "St 3:1-4,23-24; Tv 25:4-5,8-9,10,14; Lc 1:57-66",
    "paole": "Áo Lễ Linh Mục: Tím"
  },
  {
    "date": "24-12-2025",
    "title": "Lịch công giáo ngày 24-12-2025",
    "desc": "Lễ Vọng Chúa Giáng Sinh",
    "read": "Is 62:1-5; Tv 89:4-5,16-17,27-29; Cv 13:16-17,22-25; Mt 1:1-25; Mt 1:18-25; Is 9:1-6; Tv 96:1-2,2-3,11-12,132; Lc 2:1-14",
    "paole": "Áo Lễ Linh Mục: Tím"
  },
  {
    "date": "25-12-2025",
    "title": "Lịch công giáo ngày 25-12-2025",
    "desc": "Chúa Giáng Sinh",
    "read": "Is 62:11-12; Tv 97:1-6,11-123; Lc 2:15-20; Is 52:7-10; Tv 98:1,2-3,3-4,5-6; Dt 1:1-6; Ga 1:1-18; Ga 1:1-5,9-14",
    "paole": "Áo Lễ Linh Mục: Trắng"
  },
  {
    "date": "26-12-2025",
    "title": "Lịch công giáo ngày 26-12-2025",
    "desc": "Thánh Tê-pha-nô, tử đạo tiên khởi",
    "read": "Cv 6:8-10; Tv 31:3-4,6,7,8,17,21; Mt 10:17-22",
    "paole": "Áo Lễ Linh Mục: Đỏ"
  },
  {
    "date": "27-12-2025",
    "title": "Lịch công giáo ngày 27-12-2025",
    "desc": "Thánh Gio-an, tông đồ, tác giả sách Tin Mừng",
    "read": "1 Ga 1:1-4; Tv 97:1-2,5-6,11-12; Ga 20:2-8",
    "paole": "Áo Lễ Linh Mục: Trắng"
  },
  {
    "date": "28-12-2025",
    "title": "Lịch công giáo ngày 28-12-2025",
    "desc": "Thánh Gia Thất: Chúa Giê-su, Đức Maria và thánh Giu-se",
    "read": "1 Sm 1:20-22,24-28; Tv 84:2-3,5-6,9-10; 1 Ga 3:1-2,21-24; Lc 2:41-52",
    "paole": "Áo Lễ Linh Mục: Trắng"
  },
  {
    "date": "29-12-2025",
    "title": "Lịch công giáo ngày 29-12-2025",
    "desc": "Ngày thứ năm trong tuần Bát Nhật Lễ Giáng Sinh",
    "read": "1 Ga 2:3-11; Tv 96:1-2,2-3,5-6; Lc 2:22-35",
    "paole": "Áo Lễ Linh Mục: Trắng"
  },
  {
    "date": "30-12-2025",
    "title": "Lịch công giáo ngày 30-12-2025",
    "desc": "Ngày thứ sáu trong tuần Bát Nhật Lễ Giáng Sinh",
    "read": "1 Ga 2:12-17; Tv 96:7-8,8-9,10; Lc 2:36-40",
    "paole": "Áo Lễ Linh Mục: Trắng"
  },
  {
    "date": "31-12-2025",
    "title": "Lịch công giáo ngày 31-12-2025",
    "desc": "Ngày thứ bẩy trong tuần Bát Nhật Lễ Giáng Sinh",
    "read": "1 Ga 2:18-21; Tv 96:1-2,11-12,13; Ga 1:1-18",
    "paole": "Áo Lễ Linh Mục: Trắng"
  }
]